Workbook
Name IQ_CH: 110000
Name IQ_CQ: 5000
Name IQ_CY: 10000
Name IQ_DAILY: 500000
Name IQ_FH: 100000
Name IQ_FQ: 500
Name IQ_FY: 1000
Name IQ_LTM: 2000
Name IQ_MONTH: 15000
Name IQ_NTM: 6000
Name IQ_WEEK: 50000
Name IQ_YTD: 3000

Sheet FSM Complete
C2: ="Financial Statement Model for "&D5 -> Financial Statement Model for Apple
C3: $ mm except per share
C5: Company name | D5: Apple
C6: Ticker | D6: AAPL
C7: Circ break 1=off, 0=on | D7: 1
C8: Latest closing share price | D8: 171.25
C9: Latest closing share price date | D9: 43500
C10: Latest fiscal year end date | D10: 46022
C11: Shares outstanding (millions) | D11: 4745.398
A13: x | C13: INCOME STATEMENT
C14: Fiscal year | D14: =E14-1 -> 2023 | E14: =F14-1 -> 2024 | F14: =YEAR(D10) -> 2025 | G14: =F14+1 -> 2026 | H14: =G14+1 -> 2027 | I14: =H14+1 -> 2028 | J14: =I14+1 -> 2029 | K14: =J14+1 -> 2030
C15: Fiscal year end date | D15: =EOMONTH(E15,-12) -> 45291 | E15: =EOMONTH(F15,-12) -> 45657 | F15: =D10 -> 46022 | G15: =EOMONTH(F15,12) -> 46387 | H15: =EOMONTH(G15,12) -> 46752 | I15: =EOMONTH(H15,12) -> 47118 | J15: =EOMONTH(I15,12) -> 47483 | K15: =EOMONTH(J15,12) -> 47848
C17: Revenue | D17: 910488 | E17: 1041938 | F17: 1149088 | G17: =F17*(1+G37) -> 1260549.5 | H17: =G17*(1+H37) -> 1399210 | I17: =H17*(1+I37) -> 1539131 | J17: =I17*(1+J37) -> 1677652.8 | K17: =J17*(1+K37) -> 1811865
C18: Cost of sales (enter as -) | D18: -432690 | E18: -477540 | F18: -516234 | G18: =-G38*G17 -> -542036.3 | H18: =-H38*H17 -> -559683.99 | I18: =-I38*I17 -> -584869.77 | J18: =-J38*J17 -> -603955 | K18: =-K38*K17 -> -634152.75
C19: Gross Profit | D19: =SUM(D17:D18) -> 477798 | E19: =SUM(E17:E18) -> 564398 | F19: =SUM(F17:F18) -> 632854 | G19: =SUM(G17:G18) -> 718513.24 | H19: =SUM(H17:H18) -> 839525.99 | I19: =SUM(I17:I18) -> 954261.21 | J19: =SUM(J17:J18) -> 1073697.8 | K19: =SUM(K17:K18) -> 1177712.2
C20: Research & development (enter as -) | D20: -156582 | E20: -166197 | F20: -152334 | G20: =-G39*G17 -> -157568.69 | H20: =-H39*H17 -> -167905.2 | I20: =-I39*I17 -> -177000.06 | J20: =-J39*J17 -> -184541.8 | K20: =-K39*K17 -> -190245.82
C21: Sales & Marketing Expenses | D21: -296713 | E21: -311954 | F21: -311816 | G21: =-G40*G17 -> -327742.88 | H21: =-H40*H17 -> -349802.5 | I21: =-I40*I17 -> -369391.44 | J21: =-J40*J17 -> -385860.14 | K21: =-K40*K17 -> -398610.3
C22: Selling, general & administrative (enter as -) | D22: -123079 | E22: -137550 | F22: -139854 | G22: =-G17*G41 -> -144963.2 | H22: =-H17*H41 -> -153913.1 | I22: =-I17*I41 -> -161608.75 | J22: =-J17*J41 -> -167765.28 | K22: =-K17*K41 -> -172127.17
C23: Operating profit (EBIT) | D23: =SUM(D19:D22) -> -98576 | E23: =SUM(E19:E22) -> -51303 | F23: =SUM(F19:F22) -> 28850 | G23: =SUM(G19:G22) -> 88238.468 | H23: =SUM(H19:H22) -> 167905.2 | I23: =SUM(I19:I22) -> 246260.96 | J23: =SUM(J19:J22) -> 335530.55 | K23: =SUM(K19:K22) -> 416728.95
C24: Interest income | D24: 26799 | E24: 46745 | F24: 30168
C25: Interest expense (enter as -) | D25: -7646 | E25: -14812 | F25: -14076
C26: Other expense, net (enter as -) | D26: 0 | E26: 6615 | F26: 0 | G26: =F26 -> 0 | H26: =G26 -> 0 | I26: =H26 -> 0 | J26: =I26 -> 0 | K26: =J26 -> 0
C27: Pretax profit | D27: =SUM(D23:D26) -> -79423 | E27: =SUM(E23:E26) -> -12755 | F27: =SUM(F23:F26) -> 44942 | G27: =SUM(G23:G26) -> 88238.468 | H27: =SUM(H23:H26) -> 167905.2 | I27: =SUM(I23:I26) -> 246260.96 | J27: =SUM(J23:J26) -> 335530.55 | K27: =SUM(K23:K26) -> 416728.95
C28: Taxes (enter expense as -) | D28: -2341 | E28: -40 | F28: -5526 | G28: =-G42*G27 -> -11029.808 | H28: =-H42*H27 -> -21827.676 | I28: =-I42*I27 -> -33245.229 | J28: =-J42*J27 -> -46974.278 | K28: =-K42*K27 -> -60425.698
C29: Net income | D29: =SUM(D27:D28) -> -81764 | E29: =SUM(E27:E28) -> -12795 | F29: =SUM(F27:F28) -> 39416 | G29: =SUM(G27:G28) -> 77208.659 | H29: =SUM(H27:H28) -> 146077.52 | I29: =SUM(I27:I28) -> 213015.73 | J29: =SUM(J27:J28) -> 288556.28 | K29: =SUM(K27:K28) -> 356303.25
C31: Depreciation & amortization | D31: 10157 | E31: 10903 | F31: 12547 | G31: =G108 -> 13108.099 | H31: =H108 -> 14034.452 | I31: =I108 -> 14831.766 | J31: =J108 -> 16467.879 | K31: =K108 -> 18110.664
C32: EBITDA | D32: =D23+D31 -> -88419 | E32: =E23+E31 -> -40400 | F32: =F23+F31 -> 41397 | G32: =G23+G31 -> 101346.57 | H32: =H23+H31 -> 181939.65 | I32: =I23+I31 -> 261092.72 | J32: =J23+J31 -> 351998.43 | K32: =K23+K31 -> 434839.61
C33: Stock based compensation | D33: 4840 | E33: 5340 | F33: 6068 | G33: =F33*(1+G37) -> 6656.596 | H33: =G33*(1+H37) -> 7388.8216 | I33: =H33*(1+I37) -> 8127.7037 | J33: =I33*(1+J37) -> 8859.1971 | K33: =J33*(1+K37) -> 9567.9328
C34: Adjusted EBITDA | D34: =SUM(D32:D33) -> -83579 | E34: =SUM(E32:E33) -> -35060 | F34: =SUM(F32:F33) -> 47465 | G34: =SUM(G32:G33) -> 108003.16 | H34: =SUM(H32:H33) -> 189328.47 | I34: =SUM(I32:I33) -> 269220.43 | J34: =SUM(J32:J33) -> 360857.63 | K34: =SUM(K32:K33) -> 444407.55
C36: Growth rates & margins
C37: Revenue growth | E37: =E17/D17-1 -> 0.14437313 | F37: =F17/E17-1 -> 0.10283721 | G37: 0.097 | H37: 0.11 | I37: 0.1 | J37: 0.09 | K37: 0.08
C38: COGS % of Sales | D38: =-D18/D17 -> 0.47522867 | E38: =-E18/E17 -> 0.45831902 | F38: =-F18/F17 -> 0.44925541 | G38: 0.43 | H38: 0.4 | I38: 0.38 | J38: 0.36 | K38: 0.35
C39: R&D % of sales | D39: =-D20/D17 -> 0.17197591 | E39: =-E20/E17 -> 0.15950757 | F39: =-F20/F17 -> 0.13256948 | G39: 0.125 | H39: 0.12 | I39: 0.115 | J39: 0.11 | K39: 0.105
C40: S&M % of sales | D40: =-D21/D17 -> 0.32588348 | E40: =-E21/E17 -> 0.29939785 | F40: =-F21/F17 -> 0.27135955 | G40: 0.26 | H40: 0.25 | I40: 0.24 | J40: 0.23 | K40: 0.22
C41: SG&A % of sales | D41: =-D22/D17 -> 0.13517916 | E41: =-E22/E17 -> 0.13201361 | F41: =-F22/F17 -> 0.12170869 | G41: 0.115 | H41: 0.11 | I41: 0.105 | J41: 0.1 | K41: 0.095
A42: x | C42: Tax rate | D42: =-(D28/D27) -> -0.029475089 | E42: =-(E28/E27) -> -0.0031360251 | F42: =-(F28/F27) -> 0.12295848 | G42: 0.125 | H42: 0.13 | I42: 0.135 | J42: 0.14 | K42: 0.145
C44: BALANCE SHEET
C45: =C14 -> Fiscal year | E45: =E14 -> 2024 | F45: =F14 -> 2025 | G45: =G14 -> 2026 | H45: =H14 -> 2027 | I45: =I14 -> 2028 | J45: =J14 -> 2029 | K45: =K14 -> 2030
C46: =C15 -> Fiscal year end date | E46: =E15 -> 45657 | F46: =F15 -> 46022 | G46: =G15 -> 46387 | H46: =H15 -> 46752 | I46: =I15 -> 47118 | J46: =J15 -> 47483 | K46: =K15 -> 47848
C47: Cash & equivalents, ST and LT marketable securities | E47: =362546+643410 -> 1005956 | F47: =25913+40388+170799 -> 237100 | G47: =G92+F47 -> 233536.72 | H47: =H92+G47 -> 299003.35 | I47: =I92+H47 -> 433142.62 | J47: =J92+I47 -> 642935.32 | K47: =K92+J47 -> 922341.99
C48: Accounts receivable | E48: 115172 | F48: 23186 | G48: =F48*(1+G37) -> 25435.042 | H48: =G48*(1+H37) -> 28232.897 | I48: =H48*(1+I37) -> 31056.186 | J48: =I48*(1+J37) -> 33851.243 | K48: =J48*(1+K37) -> 36559.342
C49: Inventories | E49: 4855 | F49: 3956 | G49: =F49*G18/F18 -> 4153.728 | H49: =G49*H18/G18 -> 4288.9656 | I49: =H49*I18/H18 -> 4481.9691 | J49: =I49*J18/I18 -> 4628.2228 | K49: =J49*K18/J18 -> 4859.6339
C50: Operating & Finance Lease | E50: =17799+13936 -> 31735 | F50: =25809+12087 -> 37896 | G50: =F50*(1+G37) -> 41571.912 | H50: =G50*(1+H37) -> 46144.822 | I50: =H50*(1+I37) -> 50759.305 | J50: =I50*(1+J37) -> 55327.642 | K50: =J50*(1+K37) -> 59753.853
C51: Property, plant & equipment | E51: 33783 | F51: 41304 | G51: =G101 -> 45042.86 | H51: =H101 -> 48611.182 | I51: =I101 -> 51947.568 | J51: =J101 -> 55282.974 | K51: =K101 -> 58559.859
C52: Other non current assets | E52: 18177 | F52: 22283 | G52: =F52*(1+G37) -> 24444.451 | H52: =G52*(1+H37) -> 27133.341 | I52: =H52*(1+I37) -> 29846.675 | J52: =I52*(1+J37) -> 32532.875 | K52: =J52*(1+K37) -> 35135.505
C53: Total assets | E53: =SUM(E47:E52) -> 1209678 | F53: =SUM(F47:F52) -> 365725 | G53: =SUM(G47:G52) -> 374184.72 | H53: =SUM(H47:H52) -> 453414.56 | I53: =SUM(I47:I52) -> 601234.33 | J53: =SUM(J47:J52) -> 824558.28 | K53: =SUM(K47:K52) -> 1117210.2
C55: Accounts payable | E55: 44242 | F55: 55888 | G55: =F55*G18/F18 -> 58681.382 | H55: =G55*H18/G18 -> 60591.939 | I55: =H55*I18/H18 -> 63318.576 | J55: =I55*J18/I18 -> 65384.761 | K55: =J55*K18/J18 -> 68653.999
C56: Other current liabilities | E56: 30551 | F56: 32687 | G56: =F56*(1+G37) -> 35857.639 | H56: =G56*(1+H37) -> 39801.979 | I56: =H56*(1+I37) -> 43782.177 | J56: =I56*(1+J37) -> 47722.573 | K56: =J56*(1+K37) -> 51540.379
C57: Deferred revenue (current and non current) | E57: =7548+2836 -> 10384 | F57: =7543+2797 -> 10340 | G57: =F57*(1+G37) -> 11342.98 | H57: =G57*(1+H37) -> 12590.708 | I57: =H57*(1+I37) -> 13849.779 | J57: =I57*(1+J37) -> 15096.259 | K57: =J57*(1+K37) -> 16303.959
C58: Commercial paper / revolver | E58: 11977 | F58: 11964 | G58: =G137 -> 12000 | H58: =H137 -> 12000 | I58: =I137 -> 12000 | J58: =J137 -> 12000 | K58: =K137 -> 12000
C59: Long term debt (includes current portion) | E59: =6496+97207 -> 103703 | F59: =8784+93735 -> 102519 | G59: =F59 -> 102519 | H59: =G59 -> 102519 | I59: =H59 -> 102519 | J59: =I59 -> 102519 | K59: =J59 -> 102519
C60: Other non current liabilities | E60: 40415 | F60: 45180 | G60: =F60*(1+G37) -> 49562.46 | H60: =G60*(1+H37) -> 55014.331 | I60: =H60*(1+I37) -> 60515.764 | J60: =I60*(1+J37) -> 65962.182 | K60: =J60*(1+K37) -> 71239.157
C61: Total liabilities | E61: =SUM(E55:E60) -> 241272 | F61: =SUM(F55:F60) -> 258578 | G61: =SUM(G55:G60) -> 269963.46 | H61: =SUM(H55:H60) -> 282517.96 | I61: =SUM(I55:I60) -> 295985.3 | J61: =SUM(J55:J60) -> 308684.78 | K61: =SUM(K55:K60) -> 322256.49
C63: Common stock | E63: 35867 | F63: 40201 | G63: =F63+G33 -> 46857.596 | H63: =G63+H33 -> 54246.418 | I63: =H63+I33 -> 62374.121 | J63: =I63+J33 -> 71233.318 | K63: =J63+K33 -> 80801.251
C64: Retained earnings | E64: =98330 -> 98330 | F64: 70400 | G64: =G121 -> 60817.659 | H64: =H121 -> 120104.18 | I64: =I121 -> 246328.91 | J64: =J121 -> 448094.19 | K64: =K121 -> 717606.44
C65: Other comprehensive income | E65: -150 | F65: -3454 | G65: =F65 -> -3454 | H65: =G65 -> -3454 | I65: =H65 -> -3454 | J65: =I65 -> -3454 | K65: =J65 -> -3454
C66: Total equity | E66: =SUM(E63:E65) -> 134047 | F66: =SUM(F63:F65) -> 107147 | G66: =SUM(G63:G65) -> 104221.26 | H66: =SUM(H63:H65) -> 170896.6 | I66: =SUM(I63:I65) -> 305249.03 | J66: =SUM(J63:J65) -> 515873.5 | K66: =SUM(K63:K65) -> 794953.69
A68: x | C68: Balance check | E68: =ROUND(E53-E61-E66,3) -> 834359 | F68: =ROUND(F53-F61-F66,3) -> 0 | G68: =ROUND(G53-G61-G66,3) -> 0 | H68: =ROUND(H53-H61-H66,3) -> 0 | I68: =ROUND(I53-I61-I66,3) -> 0 | J68: =ROUND(J53-J61-J66,3) -> 0 | K68: =ROUND(K53-K61-K66,3) -> 0
C70: CASH FLOW STATEMENT
C71: =C14 -> Fiscal year | G71: =G14 -> 2026 | H71: =H14 -> 2027 | I71: =I14 -> 2028 | J71: =J14 -> 2029 | K71: =K14 -> 2030
C72: =C15 -> Fiscal year end date | G72: =G15 -> 46387 | H72: =H15 -> 46752 | I72: =I15 -> 47118 | J72: =J15 -> 47483 | K72: =K15 -> 47848
C74: Net income | G74: =G29 -> 77208.659 | H74: =H29 -> 146077.52 | I74: =I29 -> 213015.73 | J74: =J29 -> 288556.28 | K74: =K29 -> 356303.25
C75: Depreciation and amortization | G75: =G31 -> 13108.099 | H75: =H31 -> 14034.452 | I75: =I31 -> 14831.766 | J75: =J31 -> 16467.879 | K75: =K31 -> 18110.664
C76: Stock based compensation | G76: =G33 -> 6656.596 | H76: =H33 -> 7388.8216 | I76: =I33 -> 8127.7037 | J76: =J33 -> 8859.1971 | K76: =K33 -> 9567.9328
C77: Decreases / (Increases) in working capital assets | G77: =-1*(SUM(G48:G50)-SUM(F48:F50)) -> -6122.682 | H77: =-1*(SUM(H48:H50)-SUM(G48:G50)) -> -7506.0026 | I77: =-1*(SUM(I48:I50)-SUM(H48:H50)) -> -7630.7753 | J77: =-1*(SUM(J48:J50)-SUM(I48:I50)) -> -7509.6479 | K77: =-1*(SUM(K48:K50)-SUM(J48:J50)) -> -7365.7219
C78: Increases / (Decreases) in working capital liabilities | G78: =SUM(G55:G57)-SUM(F55:F57) -> 6967.0014 | H78: =SUM(H55:H57)-SUM(G55:G57) -> 7102.6247 | I78: =SUM(I55:I57)-SUM(H55:H57) -> 7965.906 | J78: =SUM(J55:J57)-SUM(I55:I57) -> 7253.0611 | K78: =SUM(K55:K57)-SUM(J55:J57) -> 8294.7446
C79: Other non current assets | G79: =-(G113) -> -5723.41 | H79: =-(H113) -> -6642.6641 | I79: =-(I113) -> -7062.486 | J79: =-(J113) -> -7426.7763 | K79: =-(K113) -> -7722.4517
C80: Other non current liabilities | G80: =G60-F60 -> 4382.46 | H80: =H60-G60 -> 5451.8706 | I80: =I60-H60 -> 5501.4331 | J80: =J60-I60 -> 5446.4187 | K80: =K60-J60 -> 5276.9746
C81: Cash from operating activities | G81: =SUM(G74:G80) -> 96476.724 | H81: =SUM(H74:H80) -> 165906.63 | I81: =SUM(I74:I80) -> 234749.28 | J81: =SUM(J74:J80) -> 311646.41 | K81: =SUM(K74:K80) -> 382465.39
C83: Capital expenditures | G83: =-(G99) -> -13285 | H83: =-(H99) -> -13649 | I83: =-(I99) -> -13819 | J83: =-(J99) -> -15062.71 | K83: =-(K99) -> -16267.727
C84: Cash from investing activities | G84: =IFERROR(G83,"NA") -> -13285 | H84: =IFERROR(H83,"NA") -> -13649 | I84: =IFERROR(I83,"NA") -> -13819 | J84: =IFERROR(J83,"NA") -> -15062.71 | K84: =IFERROR(K83,"NA") -> -16267.727
C86: Long term debt | G86: =G59-F59 -> 0 | H86: =H59-G59 -> 0 | I86: =I59-H59 -> 0 | J86: =J59-I59 -> 0 | K86: =K59-J59 -> 0
C87: Revolver | G87: =G58-F58 -> 36 | H87: =H58-G58 -> 0 | I87: =I58-H58 -> 0 | J87: =J58-I58 -> 0 | K87: =K58-J58 -> 0
C88: Share repurchases | G88: =G120 -> -73056 | H88: =H120 -> -73056 | I88: =I120 -> -73056 | J88: =J120 -> -73056 | K88: =K120 -> -73056
C89: Common dividends | G89: =G119 -> -13735 | H89: =H119 -> -13735 | I89: =I119 -> -13735 | J89: =J119 -> -13735 | K89: =K119 -> -13735
C90: Cash from financing activities | G90: =SUM(G86:G89) -> -86755 | H90: =SUM(H86:H89) -> -86791 | I90: =SUM(I86:I89) -> -86791 | J90: =SUM(J86:J89) -> -86791 | K90: =SUM(K86:K89) -> -86791
A92: x | C92: Net change in cash during period | G92: =G81+G84+G90 -> -3563.2763 | H92: =H81+H84+H90 -> 65466.625 | I92: =I81+I84+I90 -> 134139.28 | J92: =J81+J84+J90 -> 209792.7 | K92: =K81+K84+K90 -> 279406.67
C94: PROPERTY, PLANT & EQUIPMENT
C95: =C14 -> Fiscal year | D95: =D14 -> 2023 | E95: =E14 -> 2024 | F95: =F14 -> 2025 | G95: =G14 -> 2026 | H95: =H14 -> 2027 | I95: =I14 -> 2028 | J95: =J14 -> 2029 | K95: =K14 -> 2030
C96: =C15 -> Fiscal year end date | D96: =D15 -> 45291 | E96: =E15 -> 45657 | F96: =F15 -> 46022 | G96: =G15 -> 46387 | H96: =H15 -> 46752 | I96: =I15 -> 47118 | J96: =J15 -> 47483 | K96: =K15 -> 47848
G97: Forecast
C98: Beginning of period | G98: =F101 -> 41304 | H98: =G101 -> 45042.86 | I98: =H101 -> 48611.182 | J98: =I101 -> 51947.568 | K98: =J101 -> 55282.974
C99: Plus: Capital expenditures | D99: 12734 | E99: 12451 | F99: 13313 | G99: 13285 | H99: 13649 | I99: 13819 | J99: =I99*(1+J37) -> 15062.71 | K99: =J99*(1+K37) -> 16267.727
C100: Less: Depreciation | D100: -8300 | E100: -8200 | F100: -9300 | G100: =-(G103*G99) -> -9546.1402 | H100: =-(H103*H99) -> -10080.678 | I100: =-(I103*I99) -> -10482.614 | J100: =-(J103*J99) -> -11727.304 | K100: =-(K103*K99) -> -12990.842
C101: End of period | E101: =E51 -> 33783 | F101: =F51 -> 41304 | G101: =SUM(G98:G100) -> 45042.86 | H101: =SUM(H98:H100) -> 48611.182 | I101: =SUM(I98:I100) -> 51947.568 | J101: =SUM(J98:J100) -> 55282.974 | K101: =SUM(K98:K100) -> 58559.859
M102: Step
C103: D&A related to PP&E as a % of capex | D103: =-(D100/D99) -> 0.65179834 | E103: =-(E100/E99) -> 0.65858164 | F103: =-(F100/F99) -> 0.69856531 | G103: =F103+$M$103 -> 0.71856531 | H103: =G103+$M$103 -> 0.73856531 | I103: =H103+$M$103 -> 0.75856531 | J103: =I103+$M$103 -> 0.77856531 | K103: =J103+$M$103 -> 0.79856531 | M103: 0.02
C105: IMPUTING TOTAL DEPRECIATION & AMORTIZATION
C106: D&A not related to PP&E | D106: =D108+D100 -> 1857 | E106: =E108+E100 -> 2703 | F106: =F108+F100 -> 3247 | G106: =G107*G17 -> 3561.959 | H106: =H107*H17 -> 3953.7745 | I106: =I107*I17 -> 4349.1519 | J106: =J107*J17 -> 4740.5756 | K106: =K107*K17 -> 5119.8217
C107: as % of revenue | D107: =D106/D17 -> 0.0020395656 | E107: =E106/E17 -> 0.0025942043 | F107: =F106/F17 -> 0.0028257192 | G107: =F107 -> 0.0028257192 | H107: =G107 -> 0.0028257192 | I107: =H107 -> 0.0028257192 | J107: =I107 -> 0.0028257192 | K107: =J107 -> 0.0028257192
A108: x | C108: Depreciation & Amortization - Total | D108: =D31 -> 10157 | E108: =E31 -> 10903 | F108: =F31 -> 12547 | G108: =-G100+G106 -> 13108.099 | H108: =-H100+H106 -> 14034.452 | I108: =-I100+I106 -> 14831.766 | J108: =-J100+J106 -> 16467.879 | K108: =-K100+K106 -> 18110.664
C110: OTHER NON-CURRENT ASSETS
C111: Beginning of period | G111: =F114 -> 22283 | H111: =G114 -> 24444.451 | I111: =H114 -> 27133.341 | J111: =I114 -> 29846.675 | K111: =J114 -> 32532.875
C112: Less: Amortization of intangible assets | G112: =-(G106) -> -3561.959 | H112: =-(H106) -> -3953.7745 | I112: =-(I106) -> -4349.1519 | J112: =-(J106) -> -4740.5756 | K112: =-(K106) -> -5119.8217
C113: Plus: Additions | G113: =G114-G112-G111 -> 5723.41 | H113: =H114-H112-H111 -> 6642.6641 | I113: =I114-I112-I111 -> 7062.486 | J113: =J114-J112-J111 -> 7426.7763 | K113: =K114-K112-K111 -> 7722.4517
C114: End of period | E114: =E52 -> 18177 | F114: =F52 -> 22283 | G114: =G52 -> 24444.451 | H114: =H52 -> 27133.341 | I114: =I52 -> 29846.675 | J114: =J52 -> 32532.875 | K114: =K52 -> 35135.505
C116: RETAINED EARNINGS
C117: Beginning of period | G117: =F121 -> 70400 | H117: =G121 -> 60817.659 | I117: =H121 -> 120104.18 | J117: =I121 -> 246328.91 | K117: =J121 -> 448094.19
C118: Plus: Net income | D118: =D29 -> -81764 | E118: =E29 -> -12795 | F118: =F29 -> 39416 | G118: =G29 -> 77208.659 | H118: =H29 -> 146077.52 | I118: =I29 -> 213015.73 | J118: =J29 -> 288556.28 | K118: =K29 -> 356303.25
C119: Less: Dividends | D119: -12188 | E119: -12803 | F119: -13735 | G119: =F119 -> -13735 | H119: =G119 -> -13735 | I119: =H119 -> -13735 | J119: =I119 -> -13735 | K119: =J119 -> -13735
...

Sheet FSM
A2: x | C2: ="Financial Statement Model FIVN" -> Financial Statement Model FIVN
C3: =MVA!$B$3 -> $ and shares in thousands, except per share data
C5: Company name | D5: FIVE 9 | I5: Select an operating scenario: | L5: Weak case
C6: Ticker | D6: FIVN
C7: Circ break 1=off, 0=on | D7: 1
C8: Latest closing share price | D8: 22.52
C9: Latest closing share price date | D9: 46144
C10: Latest fiscal year end date | D10: 46022
C11: Shares outstanding (millions) | D11: 77194
A13: x | C13: INCOME STATEMENT
C14: Fiscal year | D14: =E14-1 -> 2023 | E14: =F14-1 -> 2024 | F14: =YEAR(D10) -> 2025 | G14: =F14+1 -> 2026 | H14: =G14+1 -> 2027 | I14: =H14+1 -> 2028 | J14: =I14+1 -> 2029 | K14: =J14+1 -> 2030
C15: Fiscal year end date | D15: =EOMONTH(E15,-12) -> 45291 | E15: 45657 | F15: =D10 -> 46022 | G15: =EOMONTH(F15,12) -> 46387 | H15: =EOMONTH(G15,12) -> 46752 | I15: =EOMONTH(H15,12) -> 47118 | J15: =EOMONTH(I15,12) -> 47483 | K15: =EOMONTH(J15,12) -> 47848
C17: Revenue | D17: 910488 | E17: 1041938 | F17: 1149088 | G17: =F17*(1+G37) -> 1241015 | H17: =G17*(1+H37) -> 1352706.4 | I17: =H17*(1+I37) -> 1433868.8 | J17: =I17*(1+J37) -> 1519900.9 | K17: =J17*(1+K37) -> 1611095
C18: Cost of sales (enter as -) | D18: -432690 | E18: -477540 | F18: -516234 | G18: =G19-G17 -> -1141733.8 | H18: =H19-H17 -> -1230962.8 | I18: =I19-I17 -> -1347836.7 | J18: =J19-J17 -> -1428706.8 | K18: =K19-K17 -> -1514429.3
C19: Gross Profit | D19: =SUM(D17:D18) -> 477798 | E19: =SUM(E17:E18) -> 564398 | F19: =SUM(F17:F18) -> 632854 | G19: =G17*G38 -> 99281.203 | H19: =H17*H38 -> 121743.58 | I19: =I17*I38 -> 86032.127 | J19: =J17*J38 -> 91194.054 | K19: =K17*K38 -> 96665.697
C20: Research & development (enter as -) | D20: -156582 | E20: -166197 | F20: -152334 | G20: =-G39*G17 -> -99281.203 | H20: =-H39*H17 -> -121743.58 | I20: =-I39*I17 -> -86032.127 | J20: =-J39*J17 -> -91194.054 | K20: =-K39*K17 -> -96665.697
C21: Sales and Marketing | D21: -296713 | E21: -311954 | F21: -311816
C22: Selling, general & administrative (enter as -) | D22: -123079 | E22: -137550 | F22: -139854 | G22: =-G17*G41 -> -99281.203 | H22: =-H17*H41 -> -121743.58 | I22: =-I17*I41 -> -86032.127 | J22: =-J17*J41 -> -91194.054 | K22: =-K17*K41 -> -96665.697
C23: Operating profit (EBIT) | D23: =SUM(D19:D22) -> -98576 | E23: =SUM(E19:E22) -> -51303 | F23: =SUM(F19:F22) -> 28850 | G23: =SUM(G19:G22) -> -99281.203 | H23: =SUM(H19:H22) -> -121743.58 | I23: =SUM(I19:I22) -> -86032.127 | J23: =SUM(J19:J22) -> -91194.054 | K23: =SUM(K19:K22) -> -96665.697
C24: Interest income | D24: 26799 | E24: 46745 | F24: 30168 | G24: =G158 -> #DIV/0! | H24: =H158 -> #DIV/0! | I24: =I158 -> #DIV/0! | J24: =J158 -> #DIV/0! | K24: =K158 -> #DIV/0!
C25: Interest expense (enter as -) | D25: -7646 | E25: -14812 | F25: -14076 | G25: =-G144 -> #DIV/0! | H25: =-H144 -> #DIV/0! | I25: =-I144 -> #DIV/0! | J25: =-J144 -> #DIV/0! | K25: =-K144 -> #DIV/0!
C26: Other expense, net (enter as -) | D26: 0 | E26: 6615 | F26: 0 | G26: =F26 -> 0 | H26: =G26 -> 0 | I26: =H26 -> 0 | J26: =I26 -> 0 | K26: =J26 -> 0
C27: Pretax profit | D27: =SUM(D23:D26) -> -79423 | E27: =SUM(E23:E26) -> -12755 | F27: =SUM(F23:F26) -> 44942 | G27: =SUM(G23:G26) -> #DIV/0! | H27: =SUM(H23:H26) -> #DIV/0! | I27: =SUM(I23:I26) -> #DIV/0! | J27: =SUM(J23:J26) -> #DIV/0! | K27: =SUM(K23:K26) -> #DIV/0!
C28: Taxes (enter expense as -) | D28: -2341 | E28: -40 | F28: -5526 | G28: =-G42*G27 -> #DIV/0! | H28: =-H42*H27 -> #DIV/0! | I28: =-I42*I27 -> #DIV/0! | J28: =-J42*J27 -> #DIV/0! | K28: =-K42*K27 -> #DIV/0!
C29: Net income | D29: =SUM(D27:D28) -> -81764 | E29: =SUM(E27:E28) -> -12795 | F29: =SUM(F27:F28) -> 39416 | G29: =SUM(G27:G28) -> #DIV/0! | H29: =SUM(H27:H28) -> #DIV/0! | I29: =SUM(I27:I28) -> #DIV/0! | J29: =SUM(J27:J28) -> #DIV/0! | K29: =SUM(K27:K28) -> #DIV/0!
C31: Depreciation & amortization | D31: 10157 | E31: 10903 | F31: 12547 | G31: =G108 -> #DIV/0! | H31: =H108 -> #DIV/0! | I31: =I108 -> #DIV/0! | J31: =J108 -> #DIV/0! | K31: =K108 -> #DIV/0!
C32: EBITDA | D32: =D23+D31 -> -88419 | E32: =E23+E31 -> -40400 | F32: =F23+F31 -> 41397 | G32: =G23+G31 -> #DIV/0! | H32: =H23+H31 -> #DIV/0! | I32: =I23+I31 -> #DIV/0! | J32: =J23+J31 -> #DIV/0! | K32: =K23+K31 -> #DIV/0!
C33: Stock based compensation | D33: 4840 | E33: 5340 | F33: 6068 | G33: =F33*(1+G37) -> 6553.44 | H33: =G33*(1+H37) -> 7143.2496 | I33: =H33*(1+I37) -> 7571.8446 | J33: =I33*(1+J37) -> 8026.1553 | K33: =J33*(1+K37) -> 8507.7246
C34: Adjusted EBITDA | D34: =SUM(D32:D33) -> -83579 | E34: =SUM(E32:E33) -> -35060 | F34: =SUM(F32:F33) -> 47465 | G34: =SUM(G32:G33) -> #DIV/0! | H34: =SUM(H32:H33) -> #DIV/0! | I34: =SUM(I32:I33) -> #DIV/0! | J34: =SUM(J32:J33) -> #DIV/0! | K34: =SUM(K32:K33) -> #DIV/0!
C36: Growth rates & margins
C37: Revenue growth | D37: =D17/#REF!-1 -> #REF! | E37: =E17/D17-1 -> 0.14437313 | F37: =F17/E17-1 -> 0.10283721 | G37: 0.08 | H37: 0.09 | I37: 0.06 | J37: 0.06 | K37: 0.06
C38: Gross profit margin | D38: =D19/D17 -> 0.52477133 | E38: =E19/E17 -> 0.54168098 | F38: =F19/F17 -> 0.55074459 | G38: 0.08 | H38: 0.09 | I38: 0.06 | J38: 0.06 | K38: 0.06
C39: R&D % of sales | D39: =-D20/D17 -> 0.17197591 | E39: =-E20/E17 -> 0.15950757 | F39: =-F20/F17 -> 0.13256948 | G39: 0.08 | H39: 0.09 | I39: 0.06 | J39: 0.06 | K39: 0.06
C40: S&M % of sales | D40: =-D21/D17 -> 0.32588348 | E40: =-E21/E17 -> 0.29939785 | F40: =-F21/F17 -> 0.27135955 | G40: 0.08 | H40: 0.09 | I40: 0.06 | J40: 0.06 | K40: 0.06
C41: SG&A % of sales | D41: =-D22/D17 -> 0.13517916 | E41: =-E22/E17 -> 0.13201361 | F41: =-F22/F17 -> 0.12170869 | G41: 0.08 | H41: 0.09 | I41: 0.06 | J41: 0.06 | K41: 0.06
C42: Tax rate | D42: =-(D28/D27) -> -0.029475089 | E42: =-(E28/E27) -> -0.0031360251 | F42: =-(F28/F27) -> 0.12295848 | G42: =F42 -> 0.12295848 | H42: =G42 -> 0.12295848 | I42: =H42 -> 0.12295848 | J42: =I42 -> 0.12295848 | K42: =J42 -> 0.12295848
A44: x | C44: BALANCE SHEET
C45: =C14 -> Fiscal year | D45: =D14 -> 2023 | E45: =E14 -> 2024 | F45: =F14 -> 2025 | G45: =G14 -> 2026 | H45: =H14 -> 2027 | I45: =I14 -> 2028 | J45: =J14 -> 2029 | K45: =K14 -> 2030
C46: =C15 -> Fiscal year end date | D46: =D15 -> 45291 | E46: =E15 -> 45657 | F46: =F15 -> 46022 | G46: =G15 -> 46387 | H46: =H15 -> 46752 | I46: =I15 -> 47118 | J46: =J15 -> 47483 | K46: =K15 -> 47848
C47: Cash & equivalents, ST and LT marketable securities | G47: =G92+F47 -> #DIV/0! | H47: =H92+G47 -> #DIV/0! | I47: =I92+H47 -> #DIV/0! | J47: =J92+I47 -> #DIV/0! | K47: =K92+J47 -> #DIV/0!
C48: Accounts receivable | G48: =F48*(1+G37) -> 0 | H48: =G48*(1+H37) -> 0 | I48: =H48*(1+I37) -> 0 | J48: =I48*(1+J37) -> 0 | K48: =J48*(1+K37) -> 0
C49: Inventories | G49: =F49*G18/F18 -> 0 | H49: =G49*H18/G18 -> 0 | I49: =H49*I18/H18 -> 0 | J49: =I49*J18/I18 -> 0 | K49: =J49*K18/J18 -> 0
C50: Other current assets | G50: =F50*(1+G37) -> 0 | H50: =G50*(1+H37) -> 0 | I50: =H50*(1+I37) -> 0 | J50: =I50*(1+J37) -> 0 | K50: =J50*(1+K37) -> 0
C51: Property, plant & equipment | G51: =G101 -> #DIV/0! | H51: =H101 -> #DIV/0! | I51: =I101 -> #DIV/0! | J51: =J101 -> #DIV/0! | K51: =K101 -> #DIV/0!
C52: Other non current assets | G52: =F52*(1+G37) -> 0 | H52: =G52*(1+H37) -> 0 | I52: =H52*(1+I37) -> 0 | J52: =I52*(1+J37) -> 0 | K52: =J52*(1+K37) -> 0
C53: Total assets | D53: =SUM(D47:D52) -> 0 | E53: =SUM(E47:E52) -> 0 | F53: =SUM(F47:F52) -> 0 | G53: =SUM(G47:G52) -> #DIV/0! | H53: =SUM(H47:H52) -> #DIV/0! | I53: =SUM(I47:I52) -> #DIV/0! | J53: =SUM(J47:J52) -> #DIV/0! | K53: =SUM(K47:K52) -> #DIV/0!
C55: Accounts payable | G55: =F55*G18/F18 -> 0 | H55: =G55*H18/G18 -> 0 | I55: =H55*I18/H18 -> 0 | J55: =I55*J18/I18 -> 0 | K55: =J55*K18/J18 -> 0
C56: Other current liabilities | G56: =F56*(1+G37) -> 0 | H56: =G56*(1+H37) -> 0 | I56: =H56*(1+I37) -> 0 | J56: =I56*(1+J37) -> 0 | K56: =J56*(1+K37) -> 0
C57: Deferred revenue (current) | G57: =F57*(1+G37) -> 0 | H57: =G57*(1+H37) -> 0 | I57: =H57*(1+I37) -> 0 | J57: =I57*(1+J37) -> 0 | K57: =J57*(1+K37) -> 0
C58: Commercial paper / revolver | G58: =G137 -> #DIV/0! | H58: =H137 -> #DIV/0! | I58: =I137 -> #DIV/0! | J58: =J137 -> #DIV/0! | K58: =K137 -> #DIV/0!
C59: Long term debt (includes current portion) | G59: =F59 -> 0 | H59: =G59 -> 0 | I59: =H59 -> 0 | J59: =I59 -> 0 | K59: =J59 -> 0
C60: Other non current liabilities | G60: =F60*(1+G37) -> 0 | H60: =G60*(1+H37) -> 0 | I60: =H60*(1+I37) -> 0 | J60: =I60*(1+J37) -> 0 | K60: =J60*(1+K37) -> 0
C61: Total liabilities | D61: =SUM(D55:D60) -> 0 | E61: =SUM(E55:E60) -> 0 | F61: =SUM(F55:F60) -> 0 | G61: =SUM(G55:G60) -> #DIV/0! | H61: =SUM(H55:H60) -> #DIV/0! | I61: =SUM(I55:I60) -> #DIV/0! | J61: =SUM(J55:J60) -> #DIV/0! | K61: =SUM(K55:K60) -> #DIV/0!
C63: Common stock | G63: =F63+G33 -> 6553.44 | H63: =G63+H33 -> 13696.69 | I63: =H63+I33 -> 21268.534 | J63: =I63+J33 -> 29294.689 | K63: =J63+K33 -> 37802.414
C64: Retained earnings | D64: =98330 -> 98330 | G64: =G121 -> #DIV/0! | H64: =H121 -> #DIV/0! | I64: =I121 -> #DIV/0! | J64: =J121 -> #DIV/0! | K64: =K121 -> #DIV/0!
C65: Other comprehensive income | G65: =F65 -> 0 | H65: =G65 -> 0 | I65: =H65 -> 0 | J65: =I65 -> 0 | K65: =J65 -> 0
C66: Total equity | D66: =SUM(D63:D65) -> 98330 | E66: =SUM(E63:E65) -> 0 | F66: =SUM(F63:F65) -> 0 | G66: =SUM(G63:G65) -> #DIV/0! | H66: =SUM(H63:H65) -> #DIV/0! | I66: =SUM(I63:I65) -> #DIV/0! | J66: =SUM(J63:J65) -> #DIV/0! | K66: =SUM(K63:K65) -> #DIV/0!
C68: Balance check | D68: =ROUND(D53-D61-D66,3) -> -98330 | E68: =ROUND(E53-E61-E66,3) -> 0 | F68: =ROUND(F53-F61-F66,3) -> 0 | G68: =ROUND(G53-G61-G66,3) -> #DIV/0! | H68: =ROUND(H53-H61-H66,3) -> #DIV/0! | I68: =ROUND(I53-I61-I66,3) -> #DIV/0! | J68: =ROUND(J53-J61-J66,3) -> #DIV/0! | K68: =ROUND(K53-K61-K66,3) -> #DIV/0!
A70: x | C70: CASH FLOW STATEMENT
C71: =C14 -> Fiscal year | G71: =G14 -> 2026 | H71: =H14 -> 2027 | I71: =I14 -> 2028 | J71: =J14 -> 2029 | K71: =K14 -> 2030
C72: =C15 -> Fiscal year end date | G72: =G15 -> 46387 | H72: =H15 -> 46752 | I72: =I15 -> 47118 | J72: =J15 -> 47483 | K72: =K15 -> 47848
C74: Net income | G74: =G29 -> #DIV/0! | H74: =H29 -> #DIV/0! | I74: =I29 -> #DIV/0! | J74: =J29 -> #DIV/0! | K74: =K29 -> #DIV/0!
C75: Depreciation and amortization | G75: =G31 -> #DIV/0! | H75: =H31 -> #DIV/0! | I75: =I31 -> #DIV/0! | J75: =J31 -> #DIV/0! | K75: =K31 -> #DIV/0!
C76: Stock based compensation | G76: =G33 -> 6553.44 | H76: =H33 -> 7143.2496 | I76: =I33 -> 7571.8446 | J76: =J33 -> 8026.1553 | K76: =K33 -> 8507.7246
C77: Decreases / (Increases) in working capital assets | G77: =SUM(F48:F50)-SUM(G48:G50) -> 0 | H77: =SUM(G48:G50)-SUM(H48:H50) -> 0 | I77: =SUM(H48:H50)-SUM(I48:I50) -> 0 | J77: =SUM(I48:I50)-SUM(J48:J50) -> 0 | K77: =SUM(J48:J50)-SUM(K48:K50) -> 0
C78: Increases / (Decreases) in working capital liabilities | G78: =SUM(G55:G57)-SUM(F55:F57) -> 0 | H78: =SUM(H55:H57)-SUM(G55:G57) -> 0 | I78: =SUM(I55:I57)-SUM(H55:H57) -> 0 | J78: =SUM(J55:J57)-SUM(I55:I57) -> 0 | K78: =SUM(K55:K57)-SUM(J55:J57) -> 0
C79: Other non current assets | G79: =-G113 -> -13550.76 | H79: =-H113 -> -14770.328 | I79: =-I113 -> -15656.548 | J79: =-J113 -> -16595.941 | K79: =-K113 -> -17591.697
C80: Other non current liabilities | G80: =G60-F60 -> 0 | H80: =H60-G60 -> 0 | I80: =I60-H60 -> 0 | J80: =J60-I60 -> 0 | K80: =K60-J60 -> 0
C81: Cash from operating activities | G81: =SUM(G74:G80) -> #DIV/0! | H81: =SUM(H74:H80) -> #DIV/0! | I81: =SUM(I74:I80) -> #DIV/0! | J81: =SUM(J74:J80) -> #DIV/0! | K81: =SUM(K74:K80) -> #DIV/0!
C83: Capital expenditures | G83: =-(G99) -> 0 | H83: =-(H99) -> 0 | I83: =-(I99) -> 0 | J83: =-(J99) -> 0 | K83: =-(K99) -> 0
C84: Cash from investing activities | G84: =IFERROR(G83,"NA") -> 0 | H84: =IFERROR(H83,"NA") -> 0 | I84: =IFERROR(I83,"NA") -> 0 | J84: =IFERROR(J83,"NA") -> 0 | K84: =IFERROR(K83,"NA") -> 0
C86: Long term debt | G86: =G59-F59 -> 0 | H86: =H59-G59 -> 0 | I86: =I59-H59 -> 0 | J86: =J59-I59 -> 0 | K86: =K59-J59 -> 0
C87: Commercial paper/ Revolver | G87: =G58-F58 -> #DIV/0! | H87: =H58-G58 -> #DIV/0! | I87: =I58-H58 -> #DIV/0! | J87: =J58-I58 -> #DIV/0! | K87: =K58-J58 -> #DIV/0!
C88: Share repurchases | G88: =G120 -> 0 | H88: =H120 -> 0 | I88: =I120 -> 0 | J88: =J120 -> 0 | K88: =K120 -> 0
C89: Common dividends | G89: =G119 -> #DIV/0! | H89: =H119 -> #DIV/0! | I89: =I119 -> #DIV/0! | J89: =J119 -> #DIV/0! | K89: =K119 -> #DIV/0!
C90: Cash from financing activities | G90: =SUM(G86:G89) -> #DIV/0! | H90: =SUM(H86:H89) -> #DIV/0! | I90: =SUM(I86:I89) -> #DIV/0! | J90: =SUM(J86:J89) -> #DIV/0! | K90: =SUM(K86:K89) -> #DIV/0!
C92: Net change in cash during period | G92: =G81+G84+G90 -> #DIV/0! | H92: =H81+H84+H90 -> #DIV/0! | I92: =I81+I84+I90 -> #DIV/0! | J92: =J81+J84+J90 -> #DIV/0! | K92: =K81+K84+K90 -> #DIV/0!
A94: x | C94: PROPERTY, PLANT & EQUIPMENT
C95: =C14 -> Fiscal year | D95: =D14 -> 2023 | E95: =E14 -> 2024 | F95: =F14 -> 2025 | G95: =G14 -> 2026 | H95: =H14 -> 2027 | I95: =I14 -> 2028 | J95: =J14 -> 2029 | K95: =K14 -> 2030
C96: =C15 -> Fiscal year end date | D96: =D15 -> 45291 | E96: =E15 -> 45657 | F96: =F15 -> 46022 | G96: =G15 -> 46387 | H96: =H15 -> 46752 | I96: =I15 -> 47118 | J96: =J15 -> 47483 | K96: =K15 -> 47848
G97: Forecast
C98: Beginning of period | G98: =F101 -> 0 | H98: =G101 -> #DIV/0! | I98: =H101 -> #DIV/0! | J98: =I101 -> #DIV/0! | K98: =J101 -> #DIV/0!
C99: Plus: Capital expenditures
C100: Less: Depreciation | G100: =-(G103*G99) -> #DIV/0! | H100: =-(H103*H99) -> #DIV/0! | I100: =-(I103*I99) -> #DIV/0! | J100: =-(J103*J99) -> #DIV/0! | K100: =-(K103*K99) -> #DIV/0!
C101: End of period | D101: =D51 -> 0 | E101: =E51 -> 0 | F101: =F51 -> 0 | G101: =SUM(G98:G100) -> #DIV/0! | H101: =SUM(H98:H100) -> #DIV/0! | I101: =SUM(I98:I100) -> #DIV/0! | J101: =SUM(J98:J100) -> #DIV/0! | K101: =SUM(K98:K100) -> #DIV/0!
M102: Step
C103: D&A related to PP&E as a % of capex | D103: =-(D100/D99) -> #DIV/0! | E103: =-(E100/E99) -> #DIV/0! | F103: =-(F100/F99) -> #DIV/0! | G103: =AVERAGE(D103:F103) -> #DIV/0! | H103: =G103+$M$103 -> #DIV/0! | I103: =H103+$M$103 -> #DIV/0! | J103: =I103+$M$103 -> #DIV/0! | K103: =J103+$M$103 -> #DIV/0! | M103: 0.02
A105: x | C105: IMPUTING TOTAL DEPRECIATION & AMORTIZATION
C106: D&A not related to PP&E | D106: =D108+D100 -> 10157 | E106: =E108+E100 -> 10903 | F106: =F108+F100 -> 12547 | G106: =G107*G17 -> 13550.76 | H106: =H107*H17 -> 14770.328 | I106: =I107*I17 -> 15656.548 | J106: =J107*J17 -> 16595.941 | K106: =K107*K17 -> 17591.697
C107: as % of revenue | D107: =D106/D17 -> 0.011155556 | E107: =E106/E17 -> 0.010464154 | F107: =F106/F17 -> 0.010919094 | G107: =F107 -> 0.010919094 | H107: =G107 -> 0.010919094 | I107: =H107 -> 0.010919094 | J107: =I107 -> 0.010919094 | K107: =J107 -> 0.010919094
C108: Depreciation & Amortization - Total | D108: =D31 -> 10157 | E108: =E31 -> 10903 | F108: =F31 -> 12547 | G108: =-G100+G106 -> #DIV/0! | H108: =-H100+H106 -> #DIV/0! | I108: =-I100+I106 -> #DIV/0! | J108: =-J100+J106 -> #DIV/0! | K108: =-K100+K106 -> #DIV/0!
A110: x | C110: OTHER NON-CURRENT ASSETS
C111: Beginning of period | G111: =F114 -> 0 | H111: =G114 -> 0 | I111: =H114 -> 0 | J111: =I114 -> 0 | K111: =J114 -> 0
C112: Less: Amortization of intangible assets | G112: =-(G106) -> -13550.76 | H112: =-(H106) -> -14770.328 | I112: =-(I106) -> -15656.548 | J112: =-(J106) -> -16595.941 | K112: =-(K106) -> -17591.697
C113: Plus: Additions | G113: =G114-G112-G111 -> 13550.76 | H113: =H114-H112-H111 -> 14770.328 | I113: =I114-I112-I111 -> 15656.548 | J113: =J114-J112-J111 -> 16595.941 | K113: =K114-K112-K111 -> 17591.697
C114: End of period | D114: =D52 -> 0 | E114: =E52 -> 0 | F114: =F52 -> 0 | G114: =G52 -> 0 | H114: =H52 -> 0 | I114: =I52 -> 0 | J114: =J52 -> 0 | K114: =K52 -> 0
A116: x | C116: RETAINED EARNINGS
C117: Beginning of period | G117: =F121 -> 0 | H117: =G121 -> #DIV/0! | I117: =H121 -> #DIV/0! | J117: =I121 -> #DIV/0! | K117: =J121 -> #DIV/0!
C118: Plus: Net income | D118: =D29 -> -81764 | E118: =E29 -> -12795 | F118: =F29 -> 39416 | G118: =G29 -> #DIV/0! | H118: =H29 -> #DIV/0! | I118: =I29 -> #DIV/0! | J118: =J29 -> #DIV/0! | K118: =K29 -> #DIV/0!
C119: Less: Dividends | G119: =G118*F119/F118 -> #DIV/0! | H119: =H118*G119/G118 -> #DIV/0! | I119: =I118*H119/H118 -> #DIV/0! | J119: =J118*I119/I118 -> #DIV/0! | K119: =K118*J119/J118 -> #DIV/0!
...

Sheet DCF
B2: Discounted Cash Flow Valuation
B3: =MVA!$B$3 -> $ and shares in thousands, except per share data
B4: Most recent fiscal year end | D4: 46022 | F4: Discount rate (WACC) | H4: ='[1]DCF Complete (post-WACC)'!H4 -> 0.077820797
B5: End of first fiscal year | D5: =EOMONTH(D4,12) -> 46387 | F5: Share price (Public Co) | H5: 22.24 | I5: Source: CIQ
B6: Most recent quarter end date | D6: 46112 | F6: Share price date | H6: 43888
B7: Valuation date | D7: 46144 | F7: Midyear adjustment? | H7: 0
B8: Portion of First Year Cash Flows | D8: =YEARFRAC(D7,D5) -> 0.66388889
F9: Case active: | H9: =FSM!L5 -> Weak case
A10: x | B10: Unlevered Free Cash Flows
C11: LTM | D11: Actual | E11: Forecasts
B12: Fiscal year ended | C12: =D7 -> 46144 | D12: =D4 -> 46022 | E12: =EOMONTH(D12,12) -> 46387 | F12: =EOMONTH(E12,12) -> 46752 | G12: =EOMONTH(F12,12) -> 47118 | H12: =EOMONTH(G12,12) -> 47483 | I12: =EOMONTH(H12,12) -> 47848
B14: Revenue | D14: =FSM!F17 -> 1149088
B15: % growth | E15: =IFERROR(E14/D14-1,"nm") -> -1 | F15: =IFERROR(F14/E14-1,"nm") -> nm | G15: =IFERROR(G14/F14-1,"nm") -> nm | H15: =IFERROR(H14/G14-1,"nm") -> nm | I15: =IFERROR(I14/H14-1,"nm") -> nm
B16: EBITDA | D16: =FSM!F34 -> 47465
B17: % margin | D17: =IFERROR(D16/D$14,"nm") -> 0.041306671 | E17: =IFERROR(E16/E$14,"nm") -> nm | F17: =IFERROR(F16/F$14,"nm") -> nm | G17: =IFERROR(G16/G$14,"nm") -> nm | H17: =IFERROR(H16/H$14,"nm") -> nm | I17: =IFERROR(I16/I$14,"nm") -> nm
B18: EBIT | D18: =FSM!F23 -> 28850
B19: % margin | D19: =IFERROR(D18/D$14,"nm") -> 0.025106867 | E19: =IFERROR(E18/E$14,"nm") -> nm | F19: =IFERROR(F18/F$14,"nm") -> nm | G19: =IFERROR(G18/G$14,"nm") -> nm | H19: =IFERROR(H18/H$14,"nm") -> nm | I19: =IFERROR(I18/I$14,"nm") -> nm
B21: Tax on EBIT
B22: Tax rate
B23: NOPAT (aka EBIAT)
B25: Depreciation & amortization
B26: Changes in net working capital
B27: Capital expenditures
B28: as % of revenue
B30: Unlevered free cash flows (UFCF)
B32: Net working capital (WC Assets - WC liabilities)
B33: as % of revenue
A35: x | B35: ="Present value of UFCF on "&TEXT(D7,"mmm dd, yyyy")&" valuation date" -> Present value of UFCF on May 02, 2026 valuation date
D36: Val date | E36: Yr 1 - Stub | F36: Year 2 | G36: Year 3 | H36: Year 4 | I36: Year 5
B37: Date for discounting cash flows | D37: =D7 -> 46144 | E37: =IF($H$7=1,AVERAGE(E12,D37),E12) -> 46387 | F37: =IF($H$7=1,AVERAGE(F12,E12),F12) -> 46752 | G37: =IF($H$7=1,AVERAGE(G12,F12),G12) -> 47118 | H37: =IF($H$7=1,AVERAGE(H12,G12),H12) -> 47483 | I37: =IF($H$7=1,AVERAGE(I12,H12),I12) -> 47848
B38: Unlevered free cash flows (UFCF) stub adjusted | C38: =D8 -> 0.66388889 | E38: =E30*C38 -> 0 | F38: =F30 -> 0 | G38: =G30 -> 0 | H38: =H30 -> 0 | I38: =I30 -> 0 | K38: <-Stub year counts first year cash flows starting at the valuation date
B39: Present value of unlevered free cash flows | E39: =E38/(1+$H$4)^((E37-$D$7)/365) -> 0 | F39: =F38/(1+$H$4)^((F37-$D$7)/365) -> 0 | G39: =G38/(1+$H$4)^((G37-$D$7)/365) -> 0 | H39: =H38/(1+$H$4)^((H37-$D$7)/365) -> 0 | I39: =I38/(1+$H$4)^((I37-$D$7)/365) -> 0
A41: x | B41: Terminal value - growth in perpetuity approach | E41: Terminal value - EBITDA multiple approach
B42: Long term growth rate | C42: 0.03 | E42: Terminal year EBITDA | I42: =I16 -> 0
B43: =YEAR(I12)&" FCF x (1+g)" -> 2030 FCF x (1+g) | C43: =I38*(1+C42) -> 0 | E43: EBITDA multiple | I43: 12.515439
B44: ="Terminal value in "&YEAR(I12) -> Terminal value in 2030 | C44: =C43/(H4-C42) -> 0 | E44: ="Terminal value in "&YEAR(I12) -> Terminal value in 2030 | I44: =I42*I43 -> 0
B45: Present value of terminal value | C45: =C44/(1+H4)^((I37-$D$37)/365) -> 0 | E45: Present value of terminal value | I45: =I44/(1+H4)^((I37-D37)/365) -> 0
B46: Present value of stage 1 cash flows | C46: =SUM(E39:I39) -> 0 | E46: Present value of stage 1 cash flows | I46: =C46 -> 0
B47: Total enterprise value (TEV) | C47: =C46+C45 -> 0 | E47: Enterprise value (stage 1 + 2) | I47: =SUM(I45:I46) -> 0
B49: Terminal value as % of TEV | C49: =IFERROR(C45/$C$47,"nm") -> nm | E49: Terminal value as % of TEV | I49: =+IFERROR(I45/I47,"nm") -> nm
B50: Stage 1 cash flows as % of TEV | C50: =IFERROR(1-C49,"nm") -> nm | E50: Cash flows as % of TEV | I50: =IFERROR(1-I49,"nm") -> nm
B51: Implied TV exit EBITDA multiple | C51: =IFERROR((C44/I16),"nm") -> nm | E51: Implied terminal growth rate | I51: =IFERROR((H4-I38/I44)/(1+I38/I44),"nm") -> nm
A53: x | B53: Net debt | E53: Shares outstanding
B54: Source doc | C54: Q1 2020 10Q
B55: Source date | C55: =D6 -> 46112 | G55: Source doc | H55: Date | I55: Shares
B56: Gross debt and equivalents | E56: Basic shares | G56: Q1 2020 10Q | H56: 43847 | I56: 4375.48
B57: Debt | C57: =4990+10224+93078 -> 108292 | E57: Restricted stock / RSUs | G57: Q1 2020 10Q | H57: 43827 | I57: 96.02
B58: Convertible debt | C58: ='[1]DCF Complete (post-WACC)'!C60 -> 0 | E58: Options / warrants | I58: =[1]Outputs!I60 -> 0
B59: Preferred stock | C59: ='[1]DCF Complete (post-WACC)'!C61 -> 0 | E59: Convertible debt | I59: =[1]Outputs!I61 -> 0
B60: Noncontrolling (minority) interests | C60: ='[1]DCF Complete (post-WACC)'!C62 -> 0 | E60: Convertible preferred stock | I60: =[1]Outputs!I62 -> 0
B61: Nonoperating assets | E61: Net diluted shares outstanding | I61: =SUM(I56:I60) -> 4471.5
B62: Cash | C62: =39771+67391+99899 -> 207061
B63: Equity investments | C63: 0
B65: Net debt | C65: =SUM(C57:C60)-SUM(C62:C63) -> -98769
A67: x | B67: Valuation
C68: Perpetuity | D68: EBITDA
B69: Enterprise value | C69: =C47 -> 0 | D69: =I47 -> 0
B70: Net debt | C70: =$C$65 -> -98769 | D70: =C70 -> -98769
B71: Equity value | C71: =C69-C70 -> 98769 | D71: =D69-D70 -> 98769
B72: Shares outstanding | C72: =$I$61 -> 4471.5 | D72: =C72 -> 4471.5
B73: Equity value per share | C73: =C71/C72 -> 22.088561 | D73: =D71/D72 -> 22.088561
C75: Last twelve months (LTM)
C76: Perpetuity | D76: EBITDA
B77: EV / Revenue
B78: EV / EBITDA
B79: EV / EBIT
C80: Year 1
C81: Perpetuity | D81: EBITDA
B82: EV / Revenue
B83: EV / EBITDA
B84: EV / EBIT
A86: x | B86: Outputs
D88: Equity value per share | L88: LTM EBITDA multiple
E89: Long term growth rate (g):
D90: =C73 -> 22.088561 | E90: =F90-0.005 -> 0.02 | F90: =G90-0.005 -> 0.025 | G90: 0.03 | H90: =G90+0.005 -> 0.035 | I90: =H90+0.005 -> 0.04 | L90: =C78 -> 0 | M90: =N90-0.005 -> 0.02 | N90: =O90-0.005 -> 0.025 | O90: 0.03 | P90: =O90+0.005 -> 0.035 | Q90: =P90+0.005 -> 0.04
D91: =D92+0.01 -> 0.11 | E91: 22.088561 | F91: 22.088561 | G91: 22.088561 | H91: 22.088561 | I91: 22.088561 | L91: =L92+0.01 -> 0.11 | M91: 0 | N91: 0 | O91: 0 | P91: 0 | Q91: 0
D92: =D93+0.01 -> 0.1 | E92: 22.088561 | F92: 22.088561 | G92: 22.088561 | H92: 22.088561 | I92: 22.088561 | L92: =L93+0.01 -> 0.1 | M92: 0 | N92: 0 | O92: 0 | P92: 0 | Q92: 0
C93: WACC: | D93: 0.09 | E93: 22.088561 | F93: 22.088561 | G93: 22.088561 | H93: 22.088561 | I93: 22.088561 | K93: WACC: | L93: 0.09 | M93: 0 | N93: 0 | O93: 0 | P93: 0 | Q93: 0
D94: =D93-0.01 -> 0.08 | E94: 22.088561 | F94: 22.088561 | G94: 22.088561 | H94: 22.088561 | I94: 22.088561 | L94: =L93-0.01 -> 0.08 | M94: 0 | N94: 0 | O94: 0 | P94: 0 | Q94: 0
B95: Data | D95: =D94-0.01 -> 0.07 | E95: 22.088561 | F95: 22.088561 | G95: 22.088561 | H95: 22.088561 | I95: 22.088561 | L95: =L94-0.01 -> 0.07 | M95: 0 | N95: 0 | O95: 0 | P95: 0 | Q95: 0
B96: Tables
D97: Equity value per share | L97: LTM EBITDA multiple
E98: Exit EBITDA Multiple | M98: Exit EBITDA Multiple
D99: =D73 -> 22.088561 | E99: =F99-1 -> 11 | F99: =G99-1 -> 12 | G99: 13 | H99: =G99+1 -> 14 | I99: =H99+1 -> 15 | L99: =D78 -> 0 | M99: =N99-1 -> 11 | N99: =O99-1 -> 12 | O99: 13 | P99: =O99+1 -> 14 | Q99: =P99+1 -> 15
D100: =D101+0.01 -> 0.11 | E100: 22.088561 | F100: 22.088561 | G100: 22.088561 | H100: 22.088561 | I100: 22.088561 | L100: =L101+0.01 -> 0.11 | M100: 0 | N100: 0 | O100: 0 | P100: 0 | Q100: 0
D101: =D102+0.01 -> 0.1 | E101: 22.088561 | F101: 22.088561 | G101: 22.088561 | H101: 22.088561 | I101: 22.088561 | L101: =L102+0.01 -> 0.1 | M101: 0 | N101: 0 | O101: 0 | P101: 0 | Q101: 0
C102: WACC: | D102: 0.09 | E102: 22.088561 | F102: 22.088561 | G102: 22.088561 | H102: 22.088561 | I102: 22.088561 | K102: WACC: | L102: 0.09 | M102: 0 | N102: 0 | O102: 0 | P102: 0 | Q102: 0
D103: =D102-0.01 -> 0.08 | E103: 22.088561 | F103: 22.088561 | G103: 22.088561 | H103: 22.088561 | I103: 22.088561 | L103: =L102-0.01 -> 0.08 | M103: 0 | N103: 0 | O103: 0 | P103: 0 | Q103: 0
D104: =D103-0.01 -> 0.07 | E104: 22.088561 | F104: 22.088561 | G104: 22.088561 | H104: 22.088561 | I104: 22.088561 | L104: =L103-0.01 -> 0.07 | M104: 0 | N104: 0 | O104: 0 | P104: 0 | Q104: 0
B106: Equity value range | G106: Football field
C127: Low | D127: Diff. | E127: High | O127: Low | P127: Diff. | Q127: High
B128: ="DCF Value at "&TEXT(E99,"0.0x")&"-"&TEXT(I99,"0.0x")&" Exit EBITDA Range at "&TEXT(D102,"0.0%")&" WACC" -> DCF Value at 11.0x-15.0x Exit EBITDA Range at 9.0% WACC | C128: =E102 -> 22.088561 | D128: =E128-C128 -> 0 | E128: =I102 -> 22.088561 | G128: ="LTM EBITDA Purchase Multiple at "&TEXT(M90,"0.0%")&"-"&TEXT(Q90,"0.0%")&" Perpetuity Growth at "&TEXT(L93,"0.0%")&" WACC" -> LTM EBITDA Purchase Multiple at 2.0%-4.0% Perpetuity Growth at 9.0% WACC | O128: =M93 -> 0 | P128: =Q128-O128 -> 0 | Q128: =Q93 -> 0
B129: ="DCF Value at "&TEXT(E90,"0.0%")&"-"&TEXT(I90,"0.0%")&" Perpetuity Range at "&TEXT(D102,"0.0%")&" WACC" -> DCF Value at 2.0%-4.0% Perpetuity Range at 9.0% WACC | C129: =E93 -> 22.088561 | D129: =E129-C129 -> 0 | E129: =I93 -> 22.088561 | G129: ="LTM EBITDA Purchase Multiple at "&TEXT(M102,"0.0x")&"-"&TEXT(Q102,"0.0x")&" Exit EBITDA Multiple at "&TEXT(L102,"0.0%")&" WACC" -> LTM EBITDA Purchase Multiple at 0.0x-0.0x Exit EBITDA Multiple at 9.0% WACC | O129: =M102 -> 0 | P129: =Q129-O129 -> 0 | Q129: =Q102 -> 0
B130: 52 Week Market High/Low | C130: 169.5 | D130: =E130-C130 -> 158.35 | E130: 327.85 | G130: ="LTM EBITDA Purchase Multiple at "&TEXT(L104,"0.0%")&"-"&TEXT(L100,"0.0%")&" WACC at "&TEXT(O99,"0.0x")&" Exit EBITDA" -> LTM EBITDA Purchase Multiple at 7.0%-11.0% WACC at 13.0x Exit EBITDA | O130: =O100 -> 0 | P130: =Q130-O130 -> 0 | Q130: =O104 -> 0

Sheet MVA
B2: Financials
B3: $ and shares in thousands, except per share data
D5: Actual | E5: Forecast
B6: Fiscal year ended December 31, | D6: 2025 | E6: =D6+1 -> 2026 | F6: =E6+1 -> 2027 | G6: =F6+1 -> 2028 | H6: =G6+1 -> 2029 | I6: =H6+1 -> 2030
B8: Revenue | D8: 260174 | E8: =D8*(1+E9) -> 280987.92 | F8: =E8*(1+F9) -> 306276.83 | G8: =F8*(1+G9) -> 324653.44 | H8: =G8*(1+H9) -> 344132.65 | I8: =H8*(1+I9) -> 364780.61
B9: % Revenue growth | E9: 0.08 | F9: 0.09 | G9: 0.06 | H9: 0.06 | I9: 0.06
B10: EBITDA | D10: 76477 | E10: =E11*E$8 -> 81486.497 | F10: =F11*F$8 -> 88820.282 | G10: =G11*G$8 -> 92526.231 | H10: =H11*H$8 -> 98077.805 | I10: =I11*I$8 -> 102138.57
B11: % margin | E11: 0.29 | F11: 0.29 | G11: 0.285 | H11: 0.285 | I11: 0.28
B12: EBIT | D12: 63930 | E12: =E13*E$8 -> 69123.028 | F12: =F13*F$8 -> 76569.208 | G12: =G13*G$8 -> 81163.361 | H12: =H13*H$8 -> 87753.826 | I12: =I13*I$8 -> 91195.152
B13: % margin | E13: 0.246 | F13: 0.25 | G13: 0.25 | H13: 0.255 | I13: 0.25
B15: Tax rate | E15: 0.158 | F15: 0.166 | G15: 0.167 | H15: 0.173 | I15: 0.173
B16: Capex as % of revenue | E16: =D16 -> 0 | F16: 0.039 | G16: 0.038 | H16: 0.037 | I16: 0.036
B18: Net working capital (WC Assets - WC liabilities) | D18: =22926+4106+22878+12352-46236-37720-5522 -> -27216
B19: as % of revenue | D19: =D18/D8 -> -0.10460692 | E19: =D19 -> -0.10460692 | F19: =E19 -> -0.10460692 | G19: =F19 -> -0.10460692 | H19: =G19 -> -0.10460692 | I19: =H19 -> -0.10460692
