Workbook

Sheet Output
B2: Date | C2: 45968
B3: Currency | C3: USD
X6: Trading Multiples
I7: Revenue | L7: EBITDA | N7: Net income | Q7: Revenue Growth | S7: EBITDA Margin | U7: Profit Margin | X7: EV / Revenue | Z7: EV / EBITDA | AB7: P / E
B8: Ticker | C8: Company Name | D8: Current Price | E8: Share Count | F8: Enterprise Value | G8: Market Cap | I8: 2023 | J8: 2024 | K8: 2025 | L8: 2024 | M8: 2025 | N8: 2024 | O8: 2025 | Q8: 2023-2024 | R8: 2024-2025 | S8: 2024 | T8: 2025 | U8: 2024 | V8: 2025 | X8: 2023-2024 | Y8: 2024-2025 | Z8: 2024 | AA8: 2025 | AB8: 2024 | AC8: 2025
B9: =Input!B4 -> BA | C9: =Input!C4 -> The Boeing Company | D9: =Input!D4 -> 195.21 | E9: =Input!E4 -> 760.1 | F9: =Input!F4 -> 170005 | G9: =Input!G4 -> 148378 | I9: =Input!I4 -> 77794 | J9: =Input!J4 -> 66517 | K9: =Input!K4 -> 80757 | L9: =Input!L4 -> -8988 | M9: =Input!M4 -> -6498 | N9: =Input!N4 -> -11817 | O9: =Input!O4 -> -9850 | Q9: =(J9/I9-1) -> -0.14495977 | R9: =(K9/J9-1) -> 0.21408061 | S9: =L9/J9 -> -0.13512335 | T9: =M9/K9 -> -0.080463613 | U9: =N9/J9 -> -0.17765383 | V9: =O9/K9 -> -0.12197085 | X9: =$F9/I9 -> 2.1853228 | Y9: =$F9/J9 -> 2.5558128 | Z9: =$F9/L9 -> -18.914664 | AA9: =$F9/M9 -> -26.162665 | AB9: =$G9/N9 -> -12.556317 | AC9: =$G9/O9 -> -15.063756
A10: 1 | B10: =Input!B5 -> AXON | C10: =Input!C5 -> Axon Enterprise Inc. | D10: =Input!D5 -> 572.18 | E10: =Input!E5 -> 78.416 | F10: =Input!F5 -> 44435 | G10: =Input!G5 -> 45150 | I10: =Input!I5 -> 1560.699 | J10: =Input!J5 -> 2082.526 | K10: =Input!K5 -> 2557.957 | L10: =Input!L5 -> 106.965 | M10: =Input!M5 -> 46.183 | N10: =Input!N5 -> 377.034 | O10: =Input!O5 -> 257.095 | Q10: =(J10/I10-1) -> 0.33435467 | R10: =(K10/J10-1) -> 0.22829535 | S10: =L10/J10 -> 0.051363104 | T10: =M10/K10 -> 0.018054643 | U10: =N10/J10 -> 0.18104648 | V10: =O10/K10 -> 0.10050794
A11: 2 | B11: =Input!B6 -> NOC | C11: =Input!C6 -> Northrop Grumman Corporation | D11: =Input!D6 -> 566.74 | E11: =Input!E6 -> 143.1 | F11: =Input!F6 -> 94090 | G11: =Input!G6 -> 80885 | I11: =Input!I6 -> 39290 | J11: =Input!J6 -> 41033 | K11: =Input!K6 -> 40928 | L11: =Input!L6 -> 5740 | M11: =Input!M6 -> 5578 | N11: =Input!N6 -> 4174 | O11: =Input!O6 -> 4019 | Q11: =(J11/I11-1) -> 0.044362433 | R11: =(K11/J11-1) -> -0.002558916 | S11: =L11/J11 -> 0.13988741 | T11: =M11/K11 -> 0.13628812 | U11: =N11/J11 -> 0.101723 | V11: =O11/K11 -> 0.098196833 | X11: =$F11/I11 -> 2.3947569 | Y11: =$F11/J11 -> 2.2930324 | Z11: =$F11/L11 -> 16.391986 | AA11: =$F11/M11 -> 16.868053 | AB11: =$G11/N11 -> 19.378294 | AC11: =$G11/O11 -> 20.125653
A12: 3 | B12: =Input!B7 -> LMT | C12: =Input!C7 -> Lockheed Martin Corporation | D12: =Input!D7 -> 457.07 | E12: =Input!E7 -> 231.9 | F12: =Input!F7 -> 122814 | G12: =Input!G7 -> 105764 | I12: =Input!I7 -> 67571 | J12: =Input!J7 -> 71043 | K12: =Input!K7 -> 73349 | L12: =Input!L7 -> 8572 | M12: =Input!M7 -> 7680 | N12: =Input!N7 -> 5336 | O12: =Input!O7 -> 4200 | Q12: =(J12/I12-1) -> 0.05138299 | R12: =(K12/J12-1) -> 0.032459215 | S12: =L12/J12 -> 0.12065932 | T12: =M12/K12 -> 0.1047049 | U12: =N12/J12 -> 0.075109441 | V12: =O12/K12 -> 0.057260494 | X12: =$F12/I12 -> 1.8175549 | Y12: =$F12/J12 -> 1.7287277 | Z12: =$F12/L12 -> 14.327345 | AA12: =$F12/M12 -> 15.991406 | AB12: =$G12/N12 -> 19.82084 | AC12: =$G12/O12 -> 25.181905
A13: 4 | B13: =Input!B8 -> TXN | C13: =Input!C8 -> Texas Instruments Incorporated | D13: =Input!D8 -> 159.73 | E13: =Input!E8 -> 909 | F13: =Input!F8 -> 153494 | G13: =Input!G8 -> 145134 | I13: =Input!I8 -> 17519 | J13: =Input!J8 -> 15641 | K13: =Input!K8 -> 17266 | L13: =Input!L8 -> 6921 | M13: =Input!M8 -> 7889 | N13: =Input!N8 -> 4799 | O13: =Input!O8 -> 5043 | Q13: =(J13/I13-1) -> -0.1071979 | R13: =(K13/J13-1) -> 0.10389361 | S13: =L13/J13 -> 0.44249089 | T13: =M13/K13 -> 0.45690953 | U13: =N13/J13 -> 0.30682181 | V13: =O13/K13 -> 0.29207691
A14: 5 | B14: =Input!B9 -> RTX | C14: =Input!C9 -> Raytheon Technologies Corp | D14: =Input!D9 -> 179.22 | E14: =Input!E9 -> 1343.1 | F14: =Input!F9 -> 272587 | G14: =Input!G9 -> 240293 | I14: =Input!I9 -> 68920 | J14: =Input!J9 -> 80738 | K14: =Input!K9 -> 85988 | L14: =Input!L9 -> 10902 | M14: =Input!M9 -> 13173 | N14: =Input!N9 -> 4774 | O14: =Input!O9 -> 6592 | Q14: =(J14/I14-1) -> 0.17147417 | R14: =(K14/J14-1) -> 0.065025143 | S14: =L14/J14 -> 0.13502935 | T14: =M14/K14 -> 0.15319579 | U14: =N14/J14 -> 0.05912953 | V14: =O14/K14 -> 0.07666186
A15: 6 | B15: =Input!B10 -> AAL | C15: =Input!C10 -> American Airlines Group | D15: =Input!D10 -> 12.99 | E15: =Input!E10 -> 660.358 | F15: =Input!F10 -> 26829 | G15: =Input!G10 -> 8574 | I15: =Input!I10 -> 52788 | J15: =Input!J10 -> 54211 | K15: =Input!K10 -> 54294 | L15: =Input!L10 -> 5469 | M15: =Input!M10 -> 2259 | N15: =Input!N10 -> 846 | O15: =Input!O10 -> 602 | Q15: =(J15/I15-1) -> 0.026956884 | R15: =(K15/J15-1) -> 0.0015310546 | S15: =L15/J15 -> 0.10088358 | T15: =M15/K15 -> 0.041606807 | U15: =N15/J15 -> 0.015605689 | V15: =O15/K15 -> 0.011087781 | X15: =$F15/I15 -> 0.50824051 | Y15: =$F15/J15 -> 0.49489956 | Z15: =$F15/L15 -> 4.90565 | AA15: =$F15/M15 -> 11.876494 | AB15: =$G15/N15 -> 10.134752 | AC15: =$G15/O15 -> 14.242525
A16: 7 | B16: =Input!B11 -> GD | C16: =Input!C11 -> General Dynamics Corporation | D16: =Input!D11 -> 352.42 | E16: =Input!E11 -> 269.232 | F16: =Input!F11 -> 99683 | G16: =Input!G11 -> 95195 | I16: =Input!I11 -> 42272 | J16: =Input!J11 -> 47716 | K16: =Input!K11 -> 51509 | L16: =Input!L11 -> 5682 | M16: =Input!M11 -> 6239 | N16: =Input!N11 -> 3782 | O16: =Input!O11 -> 4215 | Q16: =(J16/I16-1) -> 0.12878501 | R16: =(K16/J16-1) -> 0.079491156 | S16: =L16/J16 -> 0.11907955 | T16: =M16/K16 -> 0.12112446 | U16: =N16/J16 -> 0.079260625 | V16: =O16/K16 -> 0.08183036 | X16: =$F16/I16 -> 2.358133 | Y16: =$F16/J16 -> 2.0890896 | Z16: =$F16/L16 -> 17.543647 | AA16: =$F16/M16 -> 15.9774 | AB16: =$G16/N16 -> 25.170545 | AC16: =$G16/O16 -> 22.584816
A17: 8 | B17: =Input!B12 -> LHX | C17: =Input!C12 -> L3Harris Technologies Inc | D17: =Input!D12 -> 301.68 | E17: =Input!E12 -> 187.1 | F17: =Input!F12 -> 67088 | G17: =Input!G12 -> 56430 | I17: =Input!I12 -> 19419 | J17: =Input!J12 -> 21325 | K17: =Input!K12 -> 21740 | L17: =Input!L12 -> 3366 | M17: =Input!M12 -> 3602 | N17: =Input!N12 -> 1502 | O17: =Input!O12 -> 1759 | Q17: =(J17/I17-1) -> 0.098151295 | R17: =(K17/J17-1) -> 0.019460727 | S17: =L17/J17 -> 0.15784291 | T17: =M17/K17 -> 0.16568537 | U17: =N17/J17 -> 0.070433763 | V17: =O17/K17 -> 0.080910764 | X17: =$F17/I17 -> 3.4547608 | Y17: =$F17/J17 -> 3.1459789 | Z17: =$F17/L17 -> 19.931075 | AA17: =$F17/M17 -> 18.625208 | AB17: =$G17/N17 -> 37.569907 | AC17: =$G17/O17 -> 32.080728
B18: Mean: | D18: =AVERAGE(D10:D17) -> 325.25375 | E18: =AVERAGE(E10:E17) -> 477.77575 | F18: =AVERAGE(F10:F17) -> 110127.5 | G18: =AVERAGE(G10:G17) -> 97178.125 | I18: =AVERAGE(I10:I17) -> 38667.462 | J18: =AVERAGE(J10:J17) -> 41723.691 | K18: =AVERAGE(K10:K17) -> 43453.995 | L18: =AVERAGE(L10:L17) -> 5844.8706 | M18: =AVERAGE(M10:M17) -> 5808.2729 | N18: =AVERAGE(N10:N17) -> 3198.7542 | O18: =AVERAGE(O10:O17) -> 3335.8869 | Q18: =AVERAGE(Q10:Q17) -> 0.093533695 | R18: =AVERAGE(R10:R17) -> 0.065949668 | S18: =AVERAGE(S10:S17) -> 0.15840452 | T18: =AVERAGE(T10:T17) -> 0.1496962 | U18: =AVERAGE(U10:U17) -> 0.11114129 | V18: =AVERAGE(V10:V17) -> 0.099816619 | X18: =AVERAGE(X10:X17) -> 2.1066892 | Y18: =AVERAGE(Y10:Y17) -> 1.9503456 | Z18: =AVERAGE(Z10:Z17) -> 14.619941 | AA18: =AVERAGE(AA10:AA17) -> 15.867712 | AB18: =AVERAGE(AB10:AB17) -> 22.414867 | AC18: =AVERAGE(AC10:AC17) -> 22.843125
B19: Median: | D19: =MEDIAN(D10:D17) -> 327.05 | E19: =MEDIAN(E10:E17) -> 250.566 | F19: =MEDIAN(F10:F17) -> 96886.5 | G19: =MEDIAN(G10:G17) -> 88040 | I19: =MEDIAN(I10:I17) -> 40781 | J19: =MEDIAN(J10:J17) -> 44374.5 | K19: =MEDIAN(K10:K17) -> 46218.5 | L19: =MEDIAN(L10:L17) -> 5711 | M19: =MEDIAN(M10:M17) -> 5908.5 | N19: =MEDIAN(N10:N17) -> 3978 | O19: =MEDIAN(O10:O17) -> 4109.5 | Q19: =MEDIAN(Q10:Q17) -> 0.074767142 | R19: =MEDIAN(R10:R17) -> 0.048742179 | S19: =MEDIAN(S10:S17) -> 0.12784434 | T19: =MEDIAN(T10:T17) -> 0.12870629 | U19: =MEDIAN(U10:U17) -> 0.077185033 | V19: =MEDIAN(V10:V17) -> 0.081370562 | X19: =AVERAGE(X11:X18) -> 2.1066892 | Y19: =AVERAGE(Y11:Y18) -> 1.9503456 | Z19: =AVERAGE(Z11:Z18) -> 14.619941 | AA19: =AVERAGE(AA11:AA18) -> 15.867712 | AB19: =AVERAGE(AB11:AB18) -> 22.414867 | AC19: =AVERAGE(AC11:AC18) -> 22.843125
D21: 2025 Trading Multiple | H21: 2025 Financial Metric | L21: Enterprise Value | T21: Equity Value | X21: Implied Share Price
B22: Calculating Implied Share Price | D22: Revenue | E22: EBITA | F22: P/E | H22: Revenue | I22: EBITDA | J22: EPS | L22: Revenue | M22: EBITDA | N22: Net Income | P22: Cash | Q22: Debt | R22: Shares | T22: Revenue | U22: EBITDA | V22: Net Income | X22: Revenue | Y22: EBITDA | Z22: Net Income
B23: Minimum | D23: =MIN(Y10:Y17) -> 0.49489956 | E23: =MIN(AA10:AA17) -> 11.876494 | F23: =MIN(AC10:AC17) -> 14.242525 | H23: =$K$9 -> 80757 | I23: =$M$9 -> -6498 | J23: 7.45 | L23: =D23*H23 -> 39966.604 | M23: =E23*I23 -> -77173.458 | N23: -- | P23: {=_xldudf_QFS($B$9, "cash_and_equiv", "TTM")} -> 13801 | Q23: {=-_xldudf_QFS($B$9, "net_debt", "TTM")} -> -47180 | R23: =$E$9 -> 760.1 | T23: =L23+P23-Q23 -> 100947.6 | U23: =M23+Q23-R23 -> -125113.56 | V23: =J23*R23*F23 -> 80651.787 | X23: =T23/$R23 -> 132.80832 | Y23: =U23/$R23 -> -164.60144 | Z23: =V23/$R23 -> 106.10681
B24: Mean | D24: =AVERAGE(Y10:Y17) -> 1.9503456 | E24: =AVERAGE(AA10:AA17) -> 15.867712 | F24: =AVERAGE(AC10:AC17) -> 22.843125 | H24: =$K$9 -> 80757 | I24: =$M$9 -> -6498 | J24: 7.45 | L24: =D24*H24 -> 157504.06 | M24: =E24*I24 -> -103108.39 | N24: -- | P24: {=_xldudf_QFS($B$9, "cash_and_equiv", "TTM")} -> 13801 | Q24: {=-_xldudf_QFS($B$9, "net_debt", "TTM")} -> -47180 | R24: =$E$9 -> 760.1 | T24: =L24+P24-Q24 -> 218485.06 | U24: =M24+Q24-R24 -> -151048.49 | V24: =J24*R24*F24 -> 129354.79 | X24: =T24/$R24 -> 287.44252 | Y24: =U24/$R24 -> -198.72187 | Z24: =V24/$R24 -> 170.18128
B25: Median | D25: =MEDIAN(Y10:Y17) -> 2.0890896 | E25: =MEDIAN(AA10:AA17) -> 15.991406 | F25: =MEDIAN(AC10:AC17) -> 22.584816 | H25: =$K$9 -> 80757 | I25: =$M$9 -> -6498 | J25: 7.45 | L25: =D25*H25 -> 168708.61 | M25: =E25*I25 -> -103912.16 | N25: -- | P25: {=_xldudf_QFS($B$9, "cash_and_equiv", "TTM")} -> 13801 | Q25: {=-_xldudf_QFS($B$9, "net_debt", "TTM")} -> -47180 | R25: =$E$9 -> 760.1 | T25: =L25+P25-Q25 -> 229689.61 | U25: =M25+Q25-R25 -> -151852.26 | V25: =J25*R25*F25 -> 127892.05 | X25: =T25/$R25 -> 302.18341 | Y25: =U25/$R25 -> -199.77932 | Z25: =V25/$R25 -> 168.25688
B26: Maximum | D26: =MAX(Y10:Y17) -> 3.1459789 | E26: =MAX(AA10:AA17) -> 18.625208 | F26: =MAX(AC10:AC17) -> 32.080728 | H26: =$K$9 -> 80757 | I26: =$M$9 -> -6498 | J26: 7.45 | L26: =D26*H26 -> 254059.82 | M26: =E26*I26 -> -121026.6 | N26: -- | P26: {=_xldudf_QFS($B$9, "cash_and_equiv", "TTM")} -> 13801 | Q26: {=-_xldudf_QFS($B$9, "net_debt", "TTM")} -> -47180 | R26: =$E$9 -> 760.1 | T26: =L26+P26-Q26 -> 315040.82 | U26: =M26+Q26-R26 -> -168966.7 | V26: =J26*R26*F26 -> 181664.98 | X26: =T26/$R26 -> 414.47286 | Y26: =U26/$R26 -> -222.29536 | Z26: =V26/$R26 -> 239.00142

Sheet Input
I1: Revenue | L1: EBITDA | N1: Net Income
I2: All figures are measured in USD millions
B3: Ticker | C3: Company Name | D3: Current Price | E3: Share Count (millions) | F3: Enterprise Value (millions) | G3: Market Cap (millions) | I3: 2023 | J3: 2024 | K3: 2025 | L3: 2024 | M3: 2025 | N3: 2024 | O3: 2025
A4: TC | B4: BA | C4: {=_xldudf_QFS(B4, "name")} -> The Boeing Company | D4: {=_xldudf_QFS(B4, "price")} -> 195.21 | E4: {=_xldudf_QFS(B4, "shares_basic", "FQ")} -> 760.1 | F4: {=_xldudf_QFS($B4, "ev")} -> 170005 | G4: {=_xldudf_QFS(B4, "mkt_cap")} -> 148378 | I4: {=_xldudf_QFS($B4, "revenue", "FY2023")} -> 77794 | J4: {=_xldudf_QFS(B4, "revenue", "FY2024")} -> 66517 | K4: {=_xldudf_QFS(B4, "revenue", "TTM")} -> 80757 | L4: {=_xldudf_QFS(B4, "EBITDA", "FY2024")} -> -8988 | M4: {=_xldudf_QFS(B4, "EBITDA", "TTM")} -> -6498 | N4: {=_xldudf_QFS(B4, "net_income", "FY2024")} -> -11817 | O4: {=_xldudf_QFS(B4,"net_income","TTM")} -> -9850
A5: 1 | B5: AXON | C5: {=_xldudf_QFS(B5, "name")} -> Axon Enterprise Inc. | D5: {=_xldudf_QFS(B5, "price")} -> 572.18 | E5: {=_xldudf_QFS(B5, "shares_basic", "FQ")} -> 78.416 | F5: {=_xldudf_QFS($B5, "ev")} -> 44435 | G5: {=_xldudf_QFS(B5, "mkt_cap")} -> 45150 | I5: {=_xldudf_QFS($B5, "revenue", "FY2023")} -> 1560.699 | J5: {=_xldudf_QFS(B5, "revenue", "FY2024")} -> 2082.526 | K5: {=_xldudf_QFS(B5, "revenue", "TTM")} -> 2557.957 | L5: {=_xldudf_QFS(B5, "EBITDA", "FY2024")} -> 106.965 | M5: {=_xldudf_QFS(B5, "EBITDA", "TTM")} -> 46.183 | N5: {=_xldudf_QFS(B5, "net_income", "FY2024")} -> 377.034 | O5: {=_xldudf_QFS(B5,"net_income","TTM")} -> 257.095
A6: 2 | B6: NOC | C6: {=_xldudf_QFS(B6, "name")} -> Northrop Grumman Corporation | D6: {=_xldudf_QFS(B6, "price")} -> 566.74 | E6: {=_xldudf_QFS(B6, "shares_basic", "FQ")} -> 143.1 | F6: {=_xldudf_QFS($B6, "ev")} -> 94090 | G6: {=_xldudf_QFS(B6, "mkt_cap")} -> 80885 | I6: {=_xldudf_QFS($B6, "revenue", "FY2023")} -> 39290 | J6: {=_xldudf_QFS(B6, "revenue", "FY2024")} -> 41033 | K6: {=_xldudf_QFS(B6, "revenue", "TTM")} -> 40928 | L6: {=_xldudf_QFS(B6, "EBITDA", "FY2024")} -> 5740 | M6: {=_xldudf_QFS(B6, "EBITDA", "TTM")} -> 5578 | N6: {=_xldudf_QFS(B6, "net_income", "FY2024")} -> 4174 | O6: {=_xldudf_QFS(B6,"net_income","TTM")} -> 4019
A7: 3 | B7: LMT | C7: {=_xldudf_QFS(B7, "name")} -> Lockheed Martin Corporation | D7: {=_xldudf_QFS(B7, "price")} -> 457.07 | E7: {=_xldudf_QFS(B7, "shares_basic", "FQ")} -> 231.9 | F7: {=_xldudf_QFS($B7, "ev")} -> 122814 | G7: {=_xldudf_QFS(B7, "mkt_cap")} -> 105764 | I7: {=_xldudf_QFS($B7, "revenue", "FY2023")} -> 67571 | J7: {=_xldudf_QFS(B7, "revenue", "FY2024")} -> 71043 | K7: {=_xldudf_QFS(B7, "revenue", "TTM")} -> 73349 | L7: {=_xldudf_QFS(B7, "EBITDA", "FY2024")} -> 8572 | M7: {=_xldudf_QFS(B7, "EBITDA", "TTM")} -> 7680 | N7: {=_xldudf_QFS(B7, "net_income", "FY2024")} -> 5336 | O7: {=_xldudf_QFS(B7,"net_income","TTM")} -> 4200
A8: 4 | B8: TXN | C8: {=_xldudf_QFS(B8, "name")} -> Texas Instruments Incorporated | D8: {=_xldudf_QFS(B8, "price")} -> 159.73 | E8: {=_xldudf_QFS(B8, "shares_basic", "FQ")} -> 909 | F8: {=_xldudf_QFS($B8, "ev")} -> 153494 | G8: {=_xldudf_QFS(B8, "mkt_cap")} -> 145134 | I8: {=_xldudf_QFS($B8, "revenue", "FY2023")} -> 17519 | J8: {=_xldudf_QFS(B8, "revenue", "FY2024")} -> 15641 | K8: {=_xldudf_QFS(B8, "revenue", "TTM")} -> 17266 | L8: {=_xldudf_QFS(B8, "EBITDA", "FY2024")} -> 6921 | M8: {=_xldudf_QFS(B8, "EBITDA", "TTM")} -> 7889 | N8: {=_xldudf_QFS(B8, "net_income", "FY2024")} -> 4799 | O8: {=_xldudf_QFS(B8,"net_income","TTM")} -> 5043
A9: 5 | B9: RTX | C9: {=_xldudf_QFS(B9, "name")} -> Raytheon Technologies Corp | D9: {=_xldudf_QFS(B9, "price")} -> 179.22 | E9: {=_xldudf_QFS(B9, "shares_basic", "FQ")} -> 1343.1 | F9: {=_xldudf_QFS($B9, "ev")} -> 272587 | G9: {=_xldudf_QFS(B9, "mkt_cap")} -> 240293 | I9: {=_xldudf_QFS($B9, "revenue", "FY2023")} -> 68920 | J9: {=_xldudf_QFS(B9, "revenue", "FY2024")} -> 80738 | K9: {=_xldudf_QFS(B9, "revenue", "TTM")} -> 85988 | L9: {=_xldudf_QFS(B9, "EBITDA", "FY2024")} -> 10902 | M9: {=_xldudf_QFS(B9, "EBITDA", "TTM")} -> 13173 | N9: {=_xldudf_QFS(B9, "net_income", "FY2024")} -> 4774 | O9: {=_xldudf_QFS(B9,"net_income","TTM")} -> 6592
A10: 6 | B10: AAL | C10: {=_xldudf_QFS(B10, "name")} -> American Airlines Group | D10: {=_xldudf_QFS(B10, "price")} -> 12.99 | E10: {=_xldudf_QFS(B10, "shares_basic", "FQ")} -> 660.358 | F10: {=_xldudf_QFS($B10, "ev")} -> 26829 | G10: {=_xldudf_QFS(B10, "mkt_cap")} -> 8574 | I10: {=_xldudf_QFS($B10, "revenue", "FY2023")} -> 52788 | J10: {=_xldudf_QFS(B10, "revenue", "FY2024")} -> 54211 | K10: {=_xldudf_QFS(B10, "revenue", "TTM")} -> 54294 | L10: {=_xldudf_QFS(B10, "EBITDA", "FY2024")} -> 5469 | M10: {=_xldudf_QFS(B10, "EBITDA", "TTM")} -> 2259 | N10: {=_xldudf_QFS(B10, "net_income", "FY2024")} -> 846 | O10: {=_xldudf_QFS(B10,"net_income","TTM")} -> 602
A11: 7 | B11: GD | C11: {=_xldudf_QFS(B11, "name")} -> General Dynamics Corporation | D11: {=_xldudf_QFS(B11, "price")} -> 352.42 | E11: {=_xldudf_QFS(B11, "shares_basic", "FQ")} -> 269.232 | F11: {=_xldudf_QFS($B11, "ev")} -> 99683 | G11: {=_xldudf_QFS(B11, "mkt_cap")} -> 95195 | I11: {=_xldudf_QFS($B11, "revenue", "FY2023")} -> 42272 | J11: {=_xldudf_QFS(B11, "revenue", "FY2024")} -> 47716 | K11: {=_xldudf_QFS(B11, "revenue", "TTM")} -> 51509 | L11: {=_xldudf_QFS(B11, "EBITDA", "FY2024")} -> 5682 | M11: {=_xldudf_QFS(B11, "EBITDA", "TTM")} -> 6239 | N11: {=_xldudf_QFS(B11, "net_income", "FY2024")} -> 3782 | O11: {=_xldudf_QFS(B11,"net_income","TTM")} -> 4215
A12: 8 | B12: LHX | C12: {=_xldudf_QFS(B12, "name")} -> L3Harris Technologies Inc | D12: {=_xldudf_QFS(B12, "price")} -> 301.68 | E12: {=_xldudf_QFS(B12, "shares_basic", "FQ")} -> 187.1 | F12: {=_xldudf_QFS($B12, "ev")} -> 67088 | G12: {=_xldudf_QFS(B12, "mkt_cap")} -> 56430 | I12: {=_xldudf_QFS($B12, "revenue", "FY2023")} -> 19419 | J12: {=_xldudf_QFS(B12, "revenue", "FY2024")} -> 21325 | K12: {=_xldudf_QFS(B12, "revenue", "TTM")} -> 21740 | L12: {=_xldudf_QFS(B12, "EBITDA", "FY2024")} -> 3366 | M12: {=_xldudf_QFS(B12, "EBITDA", "TTM")} -> 3602 | N12: {=_xldudf_QFS(B12, "net_income", "FY2024")} -> 1502 | O12: {=_xldudf_QFS(B12,"net_income","TTM")} -> 1759
