Workbook

Sheet Historicals 
A3: x | B3: INCOME STATEMENT
E4: 45291 | F4: 45657 | G4: =EOMONTH(F4,12) -> 46022 | M4: 2026
B5: Revenue | E5: 910488 | F5: 1041938 | G5: 1149088
B6: Cost of Revenue | E6: 432690 | F6: 477540 | G6: 516234
B7: Gross Profit | E7: 477798 | F7: 564398 | G7: 632854
B8: Operating expenses:
C9: Research and development | E9: 156582 | F9: 166197 | G9: 152334
C10: Sales and marketing | E10: 296713 | F10: 311954 | G10: 311816
C11: General and administrative | E11: 123079 | F11: 137550 | G11: 139854
B12: Total operating expenses | E12: 576374 | F12: 615701 | G12: 604004
B13: Income (loss) from operations | E13: -98576 | F13: -51303 | G13: 28850
B14: Other income (expense), net:
C15: Interest expense | E15: -7646 | F15: -14812 | G15: -14076
C16: Gain on early extinguishment of debt | E16: 0 | F16: 6615 | G16: —
C17: Interest income and other | E17: 26799 | F17: 46745 | G17: 30168
B18: Total other income (expense), net | E18: 19153 | F18: 38548 | G18: 16092
B19: Income (loss) before income taxes | E19: -79423 | F19: -12755 | G19: 44942
B20: Provision for income taxes | E20: 2341 | F20: 40 | G20: 5526
B21: Net income (loss) | E21: -81764 | F21: -12795 | G21: 39416
B22: Net income (loss) per share:
C23: Basic | E23: -1.13 | F23: -0.17 | G23: 0.51
C24: Diluted | E24: -1.13 | F24: -0.17 | G24: 0.45
B25: Shares used in computing net income (loss) per share:
C26: Basic | E26: 72048 | F26: 74503 | G26: 76916
C27: Diluted | E27: 72048 | F27: 74503 | G27: 88002
B28: Comprehensive Income (Loss):
B29: Net income (loss) | E29: -81764 | F29: -12795 | G29: 39416
B30: Other comprehensive income | E30: 3270 | F30: 54 | G30: 261
B31: Comprehensive income (loss) | E31: -78494 | F31: -12741 | G31: 39677
A42: x | B42: BALANCE SHEET
B43: Fiscal year
B44: Fiscal year end date | E44: =E4 -> 45291 | F44: =EOMONTH(E44,12) -> 45657 | G44: =EOMONTH(F44,12) -> 46022
B46: ASSETS
B47: Current assets:
C48: Cash and cash equivalents | F48: 362546 | G48: 232084
C49: Marketable investments | F49: 643410 | G49: 464835
C50: Accounts receivable, net | F50: 115172 | G50: 130984
C51: Prepaid expenses and other current assets | F51: 50840 | G51: 43107
C52: Deferred contract acquisition costs, net | F52: 76600 | G52: 88714
B53: Total current assets | F53: 1248568 | G53: 959724
B54: Property and equipment, net | F54: 144888 | G54: 164635
B55: Operating lease right-of-use assets | F55: 38880 | G55: 46375
B56: Finance lease right-of-use assets | F56: 19269 | G56: 14216
B57: Intangible assets, net | F57: 65632 | G57: 51166
B58: Goodwill | F58: 365436 | G58: 366253
B59: Other assets | F59: 13384 | G59: 10725
B60: Deferred contract acquisition costs, net — less current portion | F60: 155157 | G60: 176976
B61: Total assets | F61: 2051214 | G61: 1790070
B63: LIABILITIES AND STOCKHOLDERS’ EQUITY
B64: Current liabilities:
C65: Accounts payable | F65: 26282 | G65: 29973
C66: Accrued and other current liabilities | F66: 83720 | G66: 84120
C67: Operating lease liabilities | F67: 11258 | G67: 12922
C68: Finance lease liabilities | F68: 7768 | G68: 8480
C69: Deferred revenue | F69: 79173 | G69: 77515
B70: Convertible senior notes | F70: 433490 | G70: 0
B71: Total current liabilities | F71: 641691 | G71: 213010
B72: Convertible senior notes — less current portion | F72: 731855 | G72: 735490
B73: Operating lease liabilities — less current portion | F73: 37071 | G73: 42116
B74: Finance lease liabilities — less current portion | F74: 11688 | G74: 6090
B75: Other long-term liabilities | F75: 6717 | G75: 7547
B76: Total liabilities | F76: 1429022 | G76: 1004253
B77: Commitments and contingencies (Note 10)
B78: Stockholders’ equity:
B79: Preferred Stock | F79: 0 | G79: 0
B80: Common Stock | F80: 76 | G80: 77
B81: Additional paid-in capital | F81: 1039125 | G81: 1163072
B82: Accumulated other comprehensive income | F82: 636 | G82: 897
B83: Accumulated deficit | F83: -417645 | G83: -378229
B84: Total stockholders’ equity | F84: 622192 | G84: 785817
B85: Total liabilities and stockholders’ equity | F85: 2051214 | G85: 1790070
A89: x | B89: CASH FLOW STATEMENT
B90: Fiscal year
B91: Fiscal year end date | E91: =E44 -> 45291 | F91: =EOMONTH(E91,12) -> 45657 | G91: =EOMONTH(F91,12) -> 46022
B93: Cash flows from operating activities:
B94: Net income (loss) | E94: -81764 | F94: -12795 | G94: 39416
B95: Adjustments:
C96: Depreciation and amortization | E96: 48515 | F96: 52905 | G96: 61764
C97: Reduction in the carrying amount of right-of-use assets | E97: 12642 | F97: 15358 | G97: 20277
C98: Amortization of deferred contract acquisition costs | E98: 55384 | F98: 71483 | G98: 86006
C99: Accretion of discount on marketable investments | E99: -11351 | F99: -20818 | G99: -7892
C100: Provision for credit losses | E100: 989 | F100: 1150 | G100: 1617
C101: Stock-based compensation | E101: 206292 | F101: 166315 | G101: 148068
C102: Amortization of discount and issuance costs on convertible senior notes | E102: 3749 | F102: 5478 | G102: 4550
C103: Gain on early extinguishment of debt | E103: 0 | F103: -6615 | G103: —
C104: Impairment charge of an equity investment | E104: 0 | F104: 1250 | G104: —
C105: Impairment charge related to closure of operating lease facilities | E105: 0 | F105: 2202 | G105: 835
C106: Interest on finance lease obligations | E106: 150 | F106: 264 | G106: 1033
C107: Deferred taxes - excluding tax benefit from acquisition | E107: 53 | F107: 647 | G107: 446
C108: Deferred taxes - tax benefit from acquisition | E108: 0 | F108: -5482 | G108: 524
C109: Other | E109: 657 | F109: -1051 | G109: 45
B110: Changes in operating assets and liabilities:
C111: Accounts receivable | E111: -9844 | F111: -14645 | G111: -17430
C112: Prepaid expenses and other current assets | E112: -3532 | F112: -12148 | G112: 7774
C113: Deferred contract acquisition costs | E113: -91544 | F113: -104957 | G113: -119940
C114: Other assets | E114: -3988 | F114: 3115 | G114: 2630
C115: Accounts payable | E115: 2932 | F115: 1057 | G115: 3190
C116: Accrued and other current liabilities | E116: -9274 | F116: 2839 | G116: -5700
C117: Deferred revenue | E117: 4958 | F117: -425 | G117: -958
C118: Other long-term liabilities | E118: 3814 | F118: -1959 | G118: -48
...

Sheet FSM
B2: X | C2: ="Financial Statement Model for "&D5 -> Financial Statement Model for FIVE 9
C3: $ thousands, except XX
C5: Company name | D5: FIVE 9 | F5: Operating lease discount rate | H5: 0.048
C6: Ticker | D6: FIVN | F6: Weighted avg. lease life | H6: 7.8
C7: Circuit breaker (1=off) | D7: 1
C8: Last closing share price | D8: 22.09
C9: Last fiscal year end date | D9: 46022
B11: X | C11: INCOME STATEMENT
C12: Fiscal year | D12: 2024 | E12: 2025 | F12: 2026 | G12: 2027 | H12: 2028 | I12: 2029 | J12: 2030 | L12: Fiscal Year | M12: 2026 | N12: 2027 | O12: 2028 | P12: 2029 | Q12: 2030
C13: Fiscal year end date | D13: 45688 | E13: 46053 | F13: =EOMONTH(E13,12) -> 46418 | G13: =EOMONTH(F13,12) -> 46783 | H13: =EOMONTH(G13,12) -> 47149 | I13: =EOMONTH(H13,12) -> 47514 | J13: =EOMONTH(I13,12) -> 47879 | L13: Fiscal year end date | M13: 46418 | N13: =EOMONTH(M13,12) -> 46783 | O13: =EOMONTH(N13,12) -> 47149 | P13: =EOMONTH(O13,12) -> 47514 | Q13: =EOMONTH(P13,12) -> 47879
R14: %Change
C15: Revenue | D15: ='Historicals '!F5 -> 1041938 | E15: ='Historicals '!G5 -> 1149088 | F15: =E15*(1+F35) -> 1286978.6 | G15: =F15*(1+G35) -> 1434981.1 | H15: =G15*(1+H35) -> 1592829 | I15: =H15*(1+I35) -> 1760076.1 | J15: =I15*(1+J35) -> 1936083.7 | L15: Gross Profit Margin | M15: =F17/F15 -> 0.5598082 | N15: =G17/G15 -> 0.56887181 | O15: =H17/H15 -> 0.57793541 | P15: =I17/I15 -> 0.58699902 | Q15: =J17/J15 -> 0.59606263 | R15: =Q15-M15 -> 0.03625443
C16: COGS | D16: =-'Historicals '!F6 -> -477540 | E16: =-'Historicals '!G6 -> -516234 | F16: =-F15*(1-F36) -> -566517.41 | G16: =-G15*(1-G36) -> -618660.81 | H16: =-H15*(1-H36) -> -672276.72 | I16: =-I15*(1-I36) -> -726913.14 | J16: =-J15*(1-J36) -> -782056.55 | L16: Operating Margin | M16: =F21/F15 -> 0.028293625 | N16: =G21/G15 -> 0.028633558 | O16: =H21/H15 -> 0.025844647 | P16: =I21/I15 -> 0.020089141 | Q16: =J21/J15 -> 0.011126597 | R16: =Q16-M16 -> -0.017167027
C17: Gross Profit | D17: =SUM(D15:D16) -> 564398 | E17: =SUM(E15:E16) -> 632854 | F17: =SUM(F15:F16) -> 720461.15 | G17: =SUM(G15:G16) -> 816320.29 | H17: =SUM(H15:H16) -> 920552.29 | I17: =SUM(I15:I16) -> 1033162.9 | J17: =SUM(J15:J16) -> 1154027.1 | L17: Profit Margin | M17: =F27/F15 -> 14888.884 | N17: =G27/G15 -> 0.27981265 | O17: =H27/H15 -> 0.35824339 | P17: =I27/I15 -> 0.37476535 | Q17: =J27/J15 -> 0.34419452 | R17: =Q17-M17 -> -14888.54
C18: Research and development | D18: =-'Historicals '!F9 -> -166197 | E18: =-'Historicals '!G9 -> -152334 | F18: =E18*(1+F37) -> -173660.76 | G18: =F18*(1+G37) -> -198494.25 | H18: =G18*(1+H37) -> -227672.9 | I18: =H18*(1+I37) -> -261368.49 | J18: =I18*(1+J37) -> -300312.4
C19: Sales and marketing | D19: =-'Historicals '!F10 -> -311954 | E19: =-'Historicals '!G10 -> -311816 | F19: =E19*(1+F38) -> -352352.08 | G19: =F19*(1+G38) -> -398157.85 | H19: =G19*(1+H38) -> -449918.37 | I19: =H19*(1+I38) -> -508407.76 | J19: =I19*(1+J38) -> -574500.77
C20: General and administrative | D20: =-'Historicals '!F11 -> -137550 | E20: =-'Historicals '!G11 -> -139854 | F20: =E20*(1+F39) -> -158035.02 | G20: =F20*(1+G39) -> -178579.57 | H20: =G20*(1+H39) -> -201794.92 | I20: =H20*(1+I39) -> -228028.26 | J20: =I20*(1+J39) -> -257671.93
C21: Operating Profit | D21: =SUM(D17:D20) -> -51303 | E21: =SUM(E17:E20) -> 28850 | F21: =SUM(F17:F20) -> 36413.289 | G21: =SUM(G17:G20) -> 41088.614 | H21: =SUM(H17:H20) -> 41166.104 | I21: =SUM(I17:I20) -> 35358.416 | J21: =SUM(J17:J20) -> 21542.024
C22: Interest Income | D22: ='Historicals '!F17 -> 46745 | E22: ='Historicals '!G17 -> 30168 | F22: 0 | G22: 0 | H22: 0 | I22: 0 | J22: 0
C23: Interest Expense | D23: ='Historicals '!F15 -> -14812 | E23: ='Historicals '!G15 -> -14076 | F23: 0 | G23: 0 | H23: 0 | I23: 0 | J23: 0
C24: Gain on early extinguishment of debt | D24: ='Historicals '!F16 -> 6615 | E24: 0 | F24: =F259 -> 19178708270 | G24: =G259 -> 360794.94 | H24: =H259 -> 529962.68 | I24: =I259 -> 624844.7 | J24: =J259 -> 645441.01
C25: Pretax Profit | D25: =SUM(D21:D24) -> -12755 | E25: =SUM(E21:E24) -> 44942 | F25: =SUM(F21:F24) -> 1.9178745e+10 | G25: =SUM(G21:G24) -> 401883.56 | H25: =SUM(H21:H24) -> 571128.78 | I25: =SUM(I21:I24) -> 660203.12 | J25: =SUM(J21:J24) -> 666983.04
C26: Tax | D26: -40 | E26: -40 | F26: =-F25*F40 -> -17069774 | G26: =-G25*G40 -> -357.69085 | H26: =-H25*H40 -> -508.3252 | I26: =-I25*I40 -> -587.60457 | J26: =-J25*J40 -> -593.63894
C27: Net Income | D27: =SUM(D25:D26) -> -12795 | E27: =SUM(E25:E26) -> 44902 | F27: =SUM(F25:F26) -> 1.9161675e+10 | G27: =SUM(G25:G26) -> 401525.87 | H27: =SUM(H25:H26) -> 570620.46 | I27: =SUM(I25:I26) -> 659615.51 | J27: =SUM(J25:J26) -> 666389.4
C29: Depreciation & Amortization | D29: ='Historicals '!F96+'Historicals '!F98 -> 124388 | E29: ='Historicals '!G96+'Historicals '!G98 -> 147770 | F29: =F177 -> 28358.242 | G29: =G177 -> 27417.51 | H29: =H177 -> 28540.786 | I29: =I177 -> 27985.952 | J29: =J177 -> 29692.863
C30: EBITDA | F30: =F21+F29 -> 64771.53 | G30: =G21+G29 -> 68506.124 | H30: =H21+H29 -> 69706.89 | I30: =I21+I29 -> 63344.368 | J30: =J21+J29 -> 51234.887
C31: Stock based compensation | D31: ='Historicals '!F95 -> 0 | E31: ='Historicals '!G95 -> 0 | F31: =E31*(1+F41) -> 0 | G31: =F31*(1+G41) -> 0 | H31: =G31*(1+H41) -> 0 | I31: =H31*(1+I41) -> 0 | J31: =I31*(1+J41) -> 0
C32: Adjusted EBITDA | F32: =SUM(F30:F31) -> 64771.53 | G32: =SUM(G30:G31) -> 68506.124 | H32: =SUM(H30:H31) -> 69706.89 | I32: =SUM(I30:I31) -> 63344.368 | J32: =SUM(J30:J31) -> 51234.887
C34: Growth rates & margins
C35: Revenue growth | E35: =E15/D15-1 -> 0.10283721 | F35: 0.12 | G35: 0.115 | H35: 0.11 | I35: 0.105 | J35: 0.1
C36: Gross profit margin | D36: =D17/D15 -> 0.54168098 | E36: =E17/E15 -> 0.55074459 | F36: =E36+(E36-D36) -> 0.5598082 | G36: =F36+(F36-E36) -> 0.56887181 | H36: =G36+(G36-F36) -> 0.57793541 | I36: =H36+(H36-G36) -> 0.58699902 | J36: =I36+(I36-H36) -> 0.59606263
C37: R&D as a % of Revenue | D37: =-D18/D15 -> 0.15950757 | E37: =-E18/E15 -> 0.13256948 | F37: 0.14 | G37: 0.143 | H37: 0.147 | I37: 0.148 | J37: 0.149
C38: S&M as a % of Revenue | D38: =-D19/D15 -> 0.29939785 | E38: =-E19/E15 -> 0.27135955 | F38: 0.13 | G38: 0.13 | H38: 0.13 | I38: 0.13 | J38: 0.13
C39: G&A as a % of Revenue | D39: =-D20/D15 -> 0.13201361 | E39: =-E20/E15 -> 0.12170869 | F39: 0.13 | G39: 0.13 | H39: 0.13 | I39: 0.13 | J39: 0.13
C40: Tax rate | D40: =IF(AND(D25<0,D26<0),D26/D25,-D26/D25) -> 0.0031360251 | E40: =IF(AND(E25<0,E26<0),E26/E25,-E26/E25) -> 0.00089003605 | F40: =E40 -> 0.00089003605 | G40: =F40 -> 0.00089003605 | H40: =G40 -> 0.00089003605 | I40: =H40 -> 0.00089003605 | J40: =I40 -> 0.00089003605
C41: Stock based compensation growth | E41: =E31/D31-1 -> #DIV/0! | F41: 0.02 | G41: 0.02 | H41: 0.02 | I41: 0.02 | J41: 0.02
B43: X | C43: BALANCE SHEET
C44: Fiscal year | D44: 2024 | E44: =D44+1 -> 2025 | F44: =E44+1 -> 2026 | G44: =F44+1 -> 2027 | H44: =G44+1 -> 2028 | I44: =H44+1 -> 2029 | J44: =I44+1 -> 2030
C45: Fiscal year end date | D45: 45688 | E45: =EOMONTH(D45,12) -> 46053 | F45: =EOMONTH(E45,12) -> 46418 | G45: =EOMONTH(F45,12) -> 46783 | H45: =EOMONTH(G45,12) -> 47149 | I45: =EOMONTH(H45,12) -> 47514 | J45: =EOMONTH(I45,12) -> 47879
C47: Cash and cash equivalents | D47: 1118785 | E47: 1421233 | F47: =E47+F109 -> 1.8543069e+10 | G47: =F47+G109 -> 1.8485602e+10 | H47: =G47+H109 -> 1.8424262e+10 | I47: =H47+I109 -> 1.8363316e+10 | J47: =I47+J109 -> 1.8303246e+10
C48: Short-term investments | D48: 4031442 | E48: 5139581 | F48: =F252 -> 6113710 | G48: =G252 -> 6938364.3 | H48: =H252 -> 10191590 | I48: =I252 -> 12016244 | J48: =J252 -> 12412327
C49: Accounts receivable | D49: 1016356 | E49: 1259737 | F49: =F118 -> 2702655 | G49: =G118 -> 3013460.3 | H49: =H118 -> 3344940.9 | I49: =I118 -> 3696159.7 | J49: =J118 -> 4065775.7
C50: Unbilled accounts receivable | D50: 40761 | E50: 50609 | F50: =E50*(F49/E49) -> 108577.16 | G50: =F50*(G49/F49) -> 121063.53 | H50: =G50*(H49/G49) -> 134380.52 | I50: =H50*(I49/H49) -> 148490.48 | J50: =I50*(J49/I49) -> 163339.52
C51: Prepaid expenses and other current assets | D51: 101458 | E51: 126470 | F51: =E51*(1+F35) -> 141646.4 | G51: =F51*(1+G35) -> 157935.74 | H51: =G51*(1+H35) -> 175308.67 | I51: =H51*(1+I35) -> 193716.08 | J51: =I51*(1+J35) -> 213087.68
C52: Property and equipment, net | D52: 55912 | E52: 70261 | F52: =F144 -> 78799.167 | G52: =G144 -> 91500.296 | H52: =H144 -> 103642.93 | I52: =I144 -> 114807.51 | J52: =J144 -> 124657.62
C53: Deferred costs, net | D53: 26383 | E53: 29961 | F53: =E53*(1+F35) -> 33556.32 | G53: =F53*(1+G35) -> 37415.297 | H53: =G53*(1+H35) -> 41530.979 | I53: =H53*(1+I35) -> 45891.732 | J53: =I53*(1+J35) -> 50480.906
C54: Lease right-of-use assets | D54: 63863 | E54: 75626 | F54: =F204 -> 73151.591 | G54: =G204 -> 70310.953 | H54: =H204 -> 66909.531 | I54: =I204 -> 63091 | J54: =J204 -> 58880.026
C55: Goodwill | D55: 439877 | E55: 439877 | F55: =E55 -> 439877 | G55: =F55 -> 439877 | H55: =G55 -> 439877 | I55: =H55 -> 439877 | J55: =I55 -> 439877
C56: Intangible assets, net | D56: 44460 | E56: 30314 | F56: =F175 -> 28392 | G56: =G175 -> 25614 | H56: =H175 -> 22832 | I56: =I175 -> 22000 | J56: =J175 -> 21168
C57: Deferred income taxes | D57: 343919 | E57: 273417 | F57: =E57*(1+F35) -> 306227.04 | G57: =F57*(1+G35) -> 341443.15 | H57: =G57*(1+H35) -> 379001.9 | I57: =H57*(1+I35) -> 418797.1 | J57: =I57*(1+J35) -> 460676.8
C58: Other long-term assets | D58: 56540 | E58: 62257 | F58: =E58*(1+F35) -> 69727.84 | G58: =F58*(1+G35) -> 77746.542 | H58: =G58*(1+H35) -> 86298.661 | I58: =H58*(1+I35) -> 95360.021 | J58: =I58*(1+J35) -> 104896.02
C59: Total assets | D59: =SUM(D47:D58) -> 7339756 | E59: =SUM(E47:E58) -> 8979343 | F59: =SUM(F47:F58) -> 1.8553166e+10 | G59: =SUM(G47:G58) -> 1.8496917e+10 | H59: =SUM(H47:H58) -> 1.8439249e+10 | I59: =SUM(I47:I58) -> 1.8380571e+10 | J59: =SUM(J47:J58) -> 1.8321362e+10
C61: Accounts payable | D61: 30447 | E61: 37644 | F61: =F129 -> -6.1763901e+08 | G61: =G129 -> -6.7448774e+08 | H61: =H129 -> -7.3294187e+08 | I61: =I129 -> -7.9250858e+08 | J61: =J129 -> -8.5262805e+08
C62: Accrued compensation and benefits | D62: 39429 | E62: 45857 | F62: =E62*(1+F35) -> 51359.84 | G62: =F62*(1+G35) -> 57266.222 | H62: =G62*(1+H35) -> 63565.506 | I62: =H62*(1+I35) -> 70239.884 | J62: =I62*(1+J35) -> 77263.873
C63: Accrued expenses and other current liabilities | D63: 35557 | E63: 45885 | F63: =E63*(1+F35) -> 51391.2 | G63: =F63*(1+G35) -> 57301.188 | H63: =G63*(1+H35) -> 63604.319 | I63: =H63*(1+I35) -> 70282.772 | J63: =I63*(1+J35) -> 77311.049
C64: Income tax payable | D64: 9024 | E64: 6698 | F64: =E64*(1+F35) -> 7501.76 | G64: =F64*(1+G35) -> 8364.4624 | H64: =G64*(1+H35) -> 9284.5533 | I64: =H64*(1+I35) -> 10259.431 | J64: =I64*(1+J35) -> 11285.374
C65: Deferred revenue | D65: 1273978 | E65: 1488819 | F65: =E65*(1+F35) -> 1667477.3 | G65: =F65*(1+G35) -> 1859237.2 | H65: =G65*(1+H35) -> 2063753.3 | I65: =H65*(1+I35) -> 2280447.3 | J65: =I65*(1+J35) -> 2508492.1
C66: Lease liabilities | D66: 9969 | E66: 12153 | F66: =F192 -> 14851 | G66: =G192 -> 18538 | H66: =H192 -> 14984 | I66: =I192 -> 14053 | J66: =J192 -> 11293
C67: Deferred income taxes | D67: 587 | E67: 558 | F67: =E67*(1+F35) -> 624.96 | G67: =F67*(1+G35) -> 696.8304 | H67: =G67*(1+H35) -> 773.48174 | I67: =H67*(1+I35) -> 854.69733 | J67: =I67*(1+J35) -> 940.16706
C68: Long-term lease liabilities | D68: 65806 | E68: 83706 | F68: =F193 -> 73378.232 | G68: =G193 -> 58008.235 | H68: =H193 -> 52872.454 | I68: =I193 -> 45627.564 | J68: =J193 -> 42579.231
C69: Other long-term liabilities | D69: 42586 | E69: 43271 | F69: =E69*(1+F35) -> 48463.52 | G69: =F69*(1+G35) -> 54036.825 | H69: =G69*(1+H35) -> 59980.876 | I69: =H69*(1+I35) -> 66278.867 | J69: =I69*(1+J35) -> 72906.754
C70: Total liabilities | D70: =SUM(D61:D69) -> 1507383 | E70: =SUM(E61:E69) -> 1764591 | F70: =SUM(F61:F69) -> -6.1572396e+08 | G70: =SUM(G61:G69) -> -6.7237429e+08 | H70: =SUM(H61:H69) -> -7.3061305e+08 | I70: =SUM(I61:I69) -> -7.8995054e+08 | J70: =SUM(J61:J69) -> -8.4982597e+08
C72: Common stock | D72: 2 | E72: 2 | F72: =E72 -> 2 | G72: =F72 -> 2 | H72: =G72 -> 2 | I72: =H72 -> 2 | J72: =I72 -> 2
C73: Additional paid-in capital | D73: 2386192 | E73: 2843089 | F73: =F217 -> 2843041 | G73: =G217 -> 2842993 | H73: =H217 -> 2842945 | I73: =I217 -> 2842897 | J73: =J217 -> 2842849
C74: Accumulated other comprehensive income (loss) | D74: -8416 | E74: 8160 | F74: =F229 -> 8160 | G74: =G229 -> 8160 | H74: =H229 -> 8160 | I74: =I229 -> 8160 | J74: =J229 -> 8160
C75: Retained earnings | D75: 3454595 | E75: 4363501 | F75: =F223 -> 1.9166038e+10 | G75: =G223 -> 1.916644e+10 | H75: =H223 -> 1.9167011e+10 | I75: =I223 -> 1.916767e+10 | J75: =J223 -> 1.9168337e+10
C76: Total stockholders’ equity | D76: =SUM(D72:D75) -> 5832373 | E76: =SUM(E72:E75) -> 7214752 | F76: =SUM(F72:F75) -> 1.916889e+10 | G76: =SUM(G72:G75) -> 1.9169291e+10 | H76: =SUM(H72:H75) -> 1.9169862e+10 | I76: =SUM(I72:I75) -> 1.9170521e+10 | J76: =SUM(J72:J75) -> 1.9171188e+10
C78: Balance Check | D78: =D59-D70-D76 -> 0 | E78: =E59-E70-E76 -> 0 | F78: =F59-F70-F76 -> 0 | G78: =G59-G70-G76 -> 0 | H78: =H59-H70-H76 -> 0 | I78: =I59-I70-I76 -> 0 | J78: =J59-J70-J76 -> 0
B80: X | C80: CASH FLOW STATEMENT
C81: Fiscal year | D81: 2024 | E81: =D81+1 -> 2025 | F81: =E81+1 -> 2026 | G81: =F81+1 -> 2027 | H81: =G81+1 -> 2028 | I81: =H81+1 -> 2029 | J81: =I81+1 -> 2030
C82: Fiscal year end date | D82: 45688 | E82: =EOMONTH(D82,12) -> 46053 | F82: =EOMONTH(E82,12) -> 46418 | G82: =EOMONTH(F82,12) -> 46783 | H82: =EOMONTH(G82,12) -> 47149 | I82: =EOMONTH(H82,12) -> 47514 | J82: =EOMONTH(I82,12) -> 47879
C84: Net income | D84: ='Historicals '!F94 -> -12795 | E84: ='Historicals '!G94 -> 39416 | F84: =F27 -> 1.9161675e+10 | G84: =G27 -> 401525.87 | H84: =H27 -> 570620.46 | I84: =I27 -> 659615.51 | J84: =J27 -> 666389.4
C85: Depreciation and amortization | F85: =F29 -> 28358.242 | G85: =G29 -> 27417.51 | H85: =H29 -> 28540.786 | I85: =I29 -> 27985.952 | J85: =J29 -> 29692.863
C86: Accretion of discount on short-term investments | F86: =F257 -> 0 | G86: =G257 -> 0 | H86: =H257 -> 0 | I86: =I257 -> 0 | J86: =J257 -> 0
C87: Stock-based compensation | F87: =F31 -> 0 | G87: =G31 -> 0 | H87: =H31 -> 0 | I87: =I31 -> 0 | J87: =J31 -> 0
C88: Deferred income taxes | F88: =E57-F57+F67-E67 -> -32743.08 | G88: =F57-G57+G67-F67 -> -35144.239 | H88: =G57-H57+H67-G67 -> -37482.095 | I88: =H57-I57+I67-H67 -> -39713.984 | J88: =I57-J57+J67-I67 -> -41794.24
C89: Deferred cost adjustment | F89: =E53-F53 -> -3595.32 | G89: =F53-G53 -> -3858.9768 | H89: =G53-H53 -> -4115.6826 | I89: =H53-I53 -> -4360.7528 | J89: =I53-J53 -> -4589.1732
C90: Change in working capital assets | F90: =SUM(E49:E51)-SUM(F49:F51) -> -1516062.5 | G90: =SUM(F49:F51)-SUM(G49:G51) -> -339581.03 | H90: =SUM(G49:G51)-SUM(H49:H51) -> -362170.55 | I90: =SUM(H49:H51)-SUM(I49:I51) -> -383736.16 | J90: =SUM(I49:I51)-SUM(J49:J51) -> -403836.63
C91: Change in working capital liabilities | F91: =SUM(F61:F65)-SUM(E61:E65) -> -6.1748618e+08 | G91: =SUM(G61:G65)-SUM(F61:F65) -> -56644292 | H91: =SUM(H61:H65)-SUM(G61:G65) -> -58236085 | I91: =SUM(I61:I65)-SUM(H61:H65) -> -59335696 | J91: =SUM(J61:J65)-SUM(I61:I65) -> -59876339
C92: Operating Lease liability | F92: =-F183+F188 -> -10129.768 | G92: =-G183+G188 -> -14182.997 | H92: =-H183+H188 -> -11189.781 | I92: =-I183+I188 -> -10675.89 | J92: =-J183+J188 -> -8308.3329
C93: other noncurrent assets | F93: =E58-F58 -> -7470.84 | G93: =F58-G58 -> -8018.7016 | H93: =G58-H58 -> -8552.1196 | I93: =H58-I58 -> -9061.3594 | J93: =I58-J58 -> -9536.0021
C94: other noncurrent liabilities | F94: =F69-E69 -> 5192.52 | G94: =G69-F69 -> 5573.3048 | H94: =H69-G69 -> 5944.0507 | I94: =I69-H69 -> 6297.9919 | J94: =J69-I69 -> 6627.8867
C95: Cash from operating activities | F95: =SUM(F84:F94) -> 1.8542652e+10 | G95: =SUM(G84:G94) -> -56610562 | H95: =SUM(H84:H94) -> -58054490 | I95: =SUM(I84:I94) -> -59089344 | J95: =SUM(J84:J94) -> -59641693
C97: Maturity of short term investments | F97: =-F250 -> 1025871 | G97: =-G250 -> 1175345.7 | H97: =-H250 -> 1746774.3 | I97: =-I250 -> 3175345.7 | J97: =-J250 -> 4603917.1
C98: Purchase of short term investments | F98: =-F249 -> -2000000 | G98: =-G249 -> -2000000 | H98: =-H249 -> -5000000 | I98: =-I249 -> -5000000 | J98: =-J249 -> -5000000
C99: Capital expenditures | F99: =-(F142+F174) -> -30000 | G99: =-(G142+G174) -> -32000 | H99: =-(H142+H174) -> -32000 | I99: =-(I142+I174) -> -32000 | J99: =-(J142+J174) -> -32000
C100: Cash from investing activities | F100: =SUM(F97:F99) -> -1004129 | G100: =SUM(G97:G99) -> -856654.29 | H100: =SUM(H97:H99) -> -3285225.7 | I100: =SUM(I97:I99) -> -1856654.3 | J100: =SUM(J97:J99) -> -428082.86
C102: Issuance of common stock upon exercise | F102: =F213 -> 0 | G102: =G213 -> 0 | H102: =H213 -> 0 | I102: =I213 -> 0 | J102: =J213 -> 0
C103: Repurchases of common stock | F103: =F216 -> -48 | G103: =G216 -> -48 | H103: =H216 -> -48 | I103: =I216 -> -48 | J103: =J216 -> -48
C104: Taxes paid related to net share settlement of equity awards | F104: =F215 -> 0 | G104: =G215 -> 0 | H104: =H215 -> 0 | I104: =I215 -> 0 | J104: =J215 -> 0
C105: Net cash provided by financing activities | F105: =SUM(F102:F104) -> -48 | G105: =SUM(G102:G104) -> -48 | H105: =SUM(H102:H104) -> -48 | I105: =SUM(I102:I104) -> -48 | J105: =SUM(J102:J104) -> -48
C107: Effect of exchange rate changes on cash, cash equivalents | F107: =F228 -> 0 | G107: =G228 -> 0 | H107: =H228 -> 0 | I107: =I228 -> 0 | J107: =J228 -> 0
C109: Net change in cash during period | F109: =F95+F100+F105+F107 -> 1.8541648e+10 | G109: =G95+G100+G105+G107 -> -57467264 | H109: =H95+H100+H105+H107 -> -61339764 | I109: =I95+I100+I105+I107 -> -60946047 | J109: =J95+J100+J105+J107 -> -60069824
C111: WORKING CAPITAL
B112: X | C112: Fiscal year | D112: 2024 | E112: =D112+1 -> 2025 | F112: =E112+1 -> 2026 | G112: =F112+1 -> 2027 | H112: =G112+1 -> 2028 | I112: =H112+1 -> 2029 | J112: =I112+1 -> 2030
C113: Fiscal year end date | D113: 45688 | E113: =EOMONTH(D113,12) -> 46053 | F113: =EOMONTH(E113,12) -> 46418 | G113: =EOMONTH(F113,12) -> 46783 | H113: =EOMONTH(G113,12) -> 47149 | I113: =EOMONTH(H113,12) -> 47514 | J113: =EOMONTH(I113,12) -> 47879
C115: ACCOUNTS RECEIVABLE
C116: Beginning of period | F116: =E118 -> 1259737 | G116: =F118 -> 2702655 | H116: =G118 -> 3013460.3 | I116: =H118 -> 3344940.9 | J116: =I118 -> 3696159.7
C117: Increases / (decreases) | F117: =F116-F118 -> -1442918 | G117: =G116-G118 -> -310805.32 | H117: =H116-H118 -> -331480.63 | I117: =I116-I118 -> -351218.8 | J117: =J116-J118 -> -369615.97
C118: End of period | E118: =E49 -> 1259737 | F118: =IF($D$120=1,E118*(1+F35),F124*F123/365) -> 2702655 | G118: =IF($D$120=1,F118*(1+G35),G124*G123/365) -> 3013460.3 | H118: =IF($D$120=1,G118*(1+H35),H124*H123/365) -> 3344940.9 | I118: =IF($D$120=1,H118*(1+I35),I124*I123/365) -> 3696159.7 | J118: =IF($D$120=1,I118*(1+J35),J124*J123/365) -> 4065775.7
...

Sheet FCFM
B2: Discounted Cash Flow Valuation
B3: $ and shares in thousands, except per share metrics
B4: Most recent fiscal year end | C4: 46053 | E4: Discount rate | G4: 0.095327269
B5: end of first fiscal year | C5: 46053 | E5: Share price | G5: {=_xll.BDP("VEEV US EQUITY", "PX_Last")} -> #NAME?
B6: most recent quarter end date | E6: Share price date | G6: =TODAY() -> 46187
B7: Valuation date | C7: 46149 | E7: Midyear adjustment (1= off) | G7: 0
B8: Portion of first year cash flows | C8: =YEARFRAC(C5,C7) -> 0.26944444
B10: Unlevered free cash flows
B11: Fiscal year | D11: 2024 | E11: 2025E | F11: 2026E | G11: 2027E | H11: 2028E | I11: 2029E | J11: 2030E
B12: Fiscal year end date | D12: 45688 | E12: =EOMONTH(D12,12) -> 46053 | F12: =EOMONTH(E12,12) -> 46418 | G12: =EOMONTH(F12,12) -> 46783 | H12: =EOMONTH(G12,12) -> 47149 | I12: =EOMONTH(H12,12) -> 47514 | J12: =EOMONTH(I12,12) -> 47879
B14: Revenue | F14: =FSM!F15 -> 1286978.6 | G14: =FSM!G15 -> 1434981.1 | H14: =FSM!H15 -> 1592829 | I14: =FSM!I15 -> 1760076.1 | J14: =FSM!J15 -> 1936083.7
B15: % growth | F15: =FSM!F15/FSM!E15-1 -> 0.12 | G15: =G14/F14-1 -> 0.115 | H15: =H14/G14-1 -> 0.11 | I15: =I14/H14-1 -> 0.105 | J15: =J14/I14-1 -> 0.1
B16: EBITDA | F16: =FSM!F30 -> 64771.53 | G16: =FSM!G30 -> 68506.124 | H16: =FSM!H30 -> 69706.89 | I16: =FSM!I30 -> 63344.368 | J16: =FSM!J30 -> 51234.887
B17: % margin | F17: =F16/F14 -> 0.050328368 | G17: =G16/G14 -> 0.047740088 | H17: =H16/H14 -> 0.043762946 | I17: =I16/I14 -> 0.035989563 | J17: =J16/J14 -> 0.026463157
B18: EBIT | F18: =FSM!F21 -> 36413.289 | G18: =FSM!G21 -> 41088.614 | H18: =FSM!H21 -> 41166.104 | I18: =FSM!I21 -> 35358.416 | J18: =FSM!J21 -> 21542.024
B19: % margin | F19: =F18/F14 -> 0.028293625 | G19: =G18/G14 -> 0.028633558 | H19: =H18/H14 -> 0.025844647 | I19: =I18/I14 -> 0.020089141 | J19: =J18/J14 -> 0.011126597
B21: Tax on EBIT | F21: =F18*-1*F22 -> -32.409139 | G21: =G18*-1*G22 -> -36.570348 | H21: =H18*-1*H22 -> -36.639316 | I21: =I18*-1*I22 -> -31.470265 | J21: =J18*-1*J22 -> -19.173178
B22: Tax rate | F22: =FSM!F40 -> 0.00089003605 | G22: =FSM!G40 -> 0.00089003605 | H22: =FSM!H40 -> 0.00089003605 | I22: =FSM!I40 -> 0.00089003605 | J22: =FSM!J40 -> 0.00089003605
B23: NOPAT | F23: =F18+F21 -> 36380.879 | G23: =G18+G21 -> 41052.044 | H23: =H18+H21 -> 41129.464 | I23: =I18+I21 -> 35326.946 | J23: =J18+J21 -> 21522.85
B25: Depreciation & Amortization | F25: =FSM!F29 -> 28358.242 | G25: =FSM!G29 -> 27417.51 | H25: =FSM!H29 -> 28540.786 | I25: =FSM!I29 -> 27985.952 | J25: =FSM!J29 -> 29692.863
B26: Stock Based Compensation | F26: =FSM!F31 -> 0 | G26: =FSM!G31 -> 0 | H26: =FSM!H31 -> 0 | I26: =FSM!I31 -> 0 | J26: =FSM!J31 -> 0
B27: Change in net working capital | F27: =F33-E33 -> 6.1918171e+08 | G27: =G33-F33 -> 57176496 | H27: =H33-G33 -> 58803692 | I27: =I33-H33 -> 59937101 | J27: =J33-I33 -> 60509246
B28: Capital expenditures | F28: =FSM!F99 -> -30000 | G28: =FSM!G99 -> -32000 | H28: =FSM!H99 -> -32000 | I28: =FSM!I99 -> -32000 | J28: =FSM!J99 -> -32000
B29: as a % of revenue | F29: =F28/F14 -> -0.023310412 | G29: =G28/G14 -> -0.022299945 | H29: =H28/H14 -> -0.020090041 | I29: =I28/I14 -> -0.018181032 | J29: =J28/J14 -> -0.016528211
B31: Unlevered free cash flows | F31: =F23+F25+F27+F28+F26 -> 6.1921645e+08 | G31: =G23+G25+G27+G28+G26 -> 57212965 | H31: =H23+H25+H27+H28+H26 -> 58841362 | I31: =I23+I25+I27+I28+I26 -> 59968414 | J31: =J23+J25+J27+J28+J26 -> 60528462
F32: =F31/F14 -> 481.13968 | G32: =G31/G14 -> 39.870188 | H32: =H31/H14 -> 36.941418 | I32: =I31/I14 -> 34.07149 | J32: =J31/J14 -> 31.26335
B33: Net working capital | E33: =SUM(FSM!E49:E51)-SUM(FSM!E61:E63) -> 1307430 | F33: =SUM(FSM!F49:F51)-SUM(FSM!F61:F63) -> 6.2048914e+08 | G33: =SUM(FSM!G49:G51)-SUM(FSM!G61:G63) -> 6.7766563e+08 | H33: =SUM(FSM!H49:H51)-SUM(FSM!H61:H63) -> 7.3646933e+08 | I33: =SUM(FSM!I49:I51)-SUM(FSM!I61:I63) -> 7.9640643e+08 | J33: =SUM(FSM!J49:J51)-SUM(FSM!J61:J63) -> 8.5691567e+08
B35: ="Present value of UFCF on "&TEXT(C7,"mmm dd, yyyy") -> Present value of UFCF on May 07, 2026
F36: 1 Yr- Target | G36: 1 | H36: =G36+1 -> 2 | I36: =H36+1 -> 3 | J36: =I36+1 -> 4
B37: Date for discounting cash flows | D37: Stub adj. | F37: =EOMONTH(C7,12) -> 46538 | G37: =IF($G$7=1,G12,AVERAGE(G12,F12)) -> 46600.5 | H37: =IF($G$7=1,H12,AVERAGE(H12,G12)) -> 46966 | I37: =IF($G$7=1,I12,AVERAGE(I12,H12)) -> 47331.5 | J37: =IF($G$7=1,J12,AVERAGE(J12,I12)) -> 47696.5
B38: Unlevered free cash flows stub adjusted | D38: =C8 -> 0.26944444 | G38: =G31*D38 -> 15415716 | H38: =H31 -> 58841362 | I38: =I31 -> 59968414 | J38: =J31 -> 60528462
B39: Present value of unlevered free cash flows | G39: =G38/(1+$G$4)^((G37-$F$37)/365) -> 15177229 | H39: =H38/(1+$G$4)^((H37-$F$37)/365) -> 52882677 | I39: =I38/(1+$G$4)^((I37-$F$37)/365) -> 49198879 | J39: =J38/(1+$G$4)^((J37-$F$37)/365) -> 45336541
B41: Terminal value- growth to perpetuity | F41: Shares outstanding
B42: Long term growth rate | D42: 0.025 | F42: Shares outstanding | J42: =163330933/1000 -> 163330.93 | K42: Update
B43: 2031 FCF | D43: =J31*(1+D42) -> 62041674 | F43: RSUs | J43: 0
B44: Terminal value in 2030 | D44: =D43/(G4-D42) -> 8.8218517e+08 | F44: PSUs | J44: 0
B45: Present value of terminal value | D45: =D44/(1+$G$4)^(($J$37-F37)/365) -> 6.6076723e+08 | F45: Stock options | J45: =15134876/1000 -> 15134.876
B46: Present value of stage 1 cash flows | D46: =SUM(H39:J39) -> 1.474181e+08 | F46: Dilutive shares outstanding | J46: =SUM(J42:J45) -> 178465.81
B47: Total enterprise value (TEV) | D47: =SUM(D45:D46) -> 8.0818533e+08
B49: Terminal value as % of TEV | D49: =D45/D47 -> 0.8175937
B50: Stage 1 cash flows as % of TEV | D50: =D46/D47 -> 0.1824063
B51: Implied TV exit EBITDA multiple | D51: =D44/J16 -> 17218.447
B53: Net debt
B54: Source document | D54: 10-K
B55: Source date | D55: 46066
B56: Gross debt and equivalents
B57: Debt | D57: =FSM!E66+FSM!E68 -> 95859
B58: Minority Interest | D58: 0
B59: Preferred stock | D59: 0
B60: Nonoperating assets
B61: Cash, cash equivalents, short-term investments | D61: =FSM!E47+FSM!E48 -> 6560814
B63: Net debt | D63: =SUM(D57:D59)-D61 -> -6464955
B65: Valuation- growth to perpetuity
B66: Enterprise value | D66: =D47 -> 8.0818533e+08
B67: Net debt | D67: =D63 -> -6464955
B68: Equity value | D68: =D66-D67 -> 8.1465028e+08
B69: Shares outstanding | D69: =J46 -> 178465.81
B70: Equity price per share | D70: =D68/D69 -> 4564.7415
B72: Year 1 multiples- growth to perpetuity
B73: EV / revenue | D73: =D66/$F$14 -> 627.97109
B74: EV / EBITDA | D74: =D66/$F$16 -> 12477.478
B75: EV / EBIT | D75: =D66/$F$18 -> 22194.791
B77: Sensitvity Analysis
C79: Equity value per share
C80: Long term growth rate (g):
C81: =D70 -> 4564.7415 | D81: =E81-0.0025 -> 0.02 | E81: =F81-0.0025 -> 0.0225 | F81: 0.025 | G81: =F81+0.0025 -> 0.0275 | H81: =G81+0.0025 -> 0.03
B82: Discount rate | C82: =C83-0.005 -> 0.099742474 | D82: 4063.4161 | E82: 4175.3685 | F82: 4294.81 | G82: 4422.5183 | H82: 4559.3823
C83: =C84-0.005 -> 0.10474247 | D83: 3823.1406 | E83: 3921.1119 | F83: 4025.2262 | G83: 4136.08 | H83: 4254.3495
C84: 0.10974247 | D84: 3609.6496 | E84: 3696.0084 | F84: 3787.4626 | G84: 3884.4769 | H84: 3987.5741
C85: =C84+0.005 -> 0.11474247 | D85: 3418.7024 | E85: 3495.3172 | F85: 3576.2006 | G85: 3661.7195 | H85: 3752.2843
C86: =C85+0.005 -> 0.11974247 | D86: 3246.9085 | E86: 3315.2725 | F86: 3387.2443 | G86: 3463.1173 | H86: 3543.2176
B88: Check | C88: =IF(C84=G4,"Ok","Check Discount Rate") -> Check Discount Rate

Sheet RIM
B2: Residual Income Valuation
B3: $ and shares in thousands, except per share
B5: Most recent fiscal year end | C5: =FCFM!C4 -> 46053 | E5: Cost of Equity | G5: 0.10999824
B6: end of first fiscal year | C6: =FCFM!C5 -> 46053 | E6: Share price | G6: =FCFM!G5 -> #NAME?
B7: most recent quarter end date | C7: =FCFM!C6 -> 0 | E7: Share price date | G7: =TODAY() -> 46187
B8: Valuation date | C8: =FCFM!C7 -> 46149
B10: Residual Income
B11: Fiscal year | D11: 2025E | E11: 2026E | F11: 2027E | G11: 2028E | H11: 2029E | I11: 2030E
B12: Fiscal year end date | D12: 46053 | E12: =EOMONTH(D12,12) -> 46418 | F12: =EOMONTH(E12,12) -> 46783 | G12: =EOMONTH(F12,12) -> 47149 | H12: =EOMONTH(G12,12) -> 47514 | I12: =EOMONTH(H12,12) -> 47879
E14: 1 Yr- Target | F14: 1 | G14: 2 | H14: 3 | I14: 4
E15: =EOMONTH(C8,12) -> 46538 | F15: =F12 -> 46783 | G15: =G12 -> 47149 | H15: =H12 -> 47514 | I15: =I12 -> 47879
B16: Earnings per share | C16: ω: | D16: 0.5 | E16: =FSM!F268 -> 103199.62 | F16: =FSM!G268 -> 2.120108 | G16: =FSM!H268 -> 2.9538717 | H16: =FSM!I268 -> 3.3476109 | I16: =FSM!J268 -> 3.3156755
B17: Book value per share | E17: =FSM!F271 -> 103238.48 | F17: =E17+F16 -> 103240.6 | G17: =F17+G16 -> 103243.55 | H17: =G17+H16 -> 103246.9 | I17: =H17+I16 -> 103250.21
B18: Residual Income | F18: =F16-(F17*$G$5) -> -11354.164 | G18: =G16-(G17*$G$5) -> -11353.655 | H18: =H16-(H17*$G$5) -> -11353.629 | I18: =I16-(I17*$G$5) -> -11354.026
B19: Present Value of Residual Incomes | F19: =F18/(1+$G$5)^((F15-$E$15)/365) -> -10586.035 | G19: =G18/(1+$G$5)^((G15-$E$15)/365) -> -9533.8302 | H19: =H18/(1+$G$5)^((H15-$E$15)/365) -> -8589.0306 | I19: =I18/(1+$G$5)^((I15-$E$15)/365) -> -7738.148
K20: If time adjust for foreign currency translation gains / losss, hedginnig gain / loss
B21: Terminal value- growth to perpetuity
B22: Terminal growth rate | D22: =FCFM!D42 -> 0.025
B23: 2031 Residual income | D23: =I18*(1+D22) -> -11637.877
B24: Terminal value | D24: =D23/(1+G5-D16) -> -19078.541
B25: Present Value of terminal value | D25: =D24/(1+$G$5)^((I15-E15)/365) -> -13002.663
B26: Present value of term 1 Residual Income | D26: =SUM(G19:I19) -> -25861.009
B27: 2026 BVPS | D27: =F17 -> 103240.6
B28: 12-month price target | D28: =SUM(D25:D27) -> 64376.925
B30: Sensitvity Analysis
C32: Equity value per share
C33: Long term growth rate (g):
C34: =D28 -> 64376.925 | D34: =E34-0.0025 -> 0.02 | E34: =F34-0.0025 -> 0.0225 | F34: 0.025 | G34: =F34+0.0025 -> 0.0275 | H34: =G34+0.0025 -> 0.03
B35: Discount rate | C35: =C36-0.005 -> 0.099998237 | D35: 66807.004 | E35: 66776.703 | F35: 66746.402 | G35: 66716.1 | H35: 66685.799
C36: =C37-0.005 -> 0.10499824 | D36: 65602.032 | E36: 65570.999 | F36: 65539.967 | G36: 65508.934 | H36: 65477.902
C37: 0.10999824 | D37: 64440.352 | E37: 64408.639 | F37: 64376.925 | G37: 64345.211 | H37: 64313.497
C38: =C37+0.005 -> 0.11499824 | D38: 63320.355 | E38: 63288.008 | F38: 63255.66 | G38: 63223.312 | H38: 63190.965
C39: =C38+0.005 -> 0.11999824 | D39: 62240.498 | E39: 62207.561 | F39: 62174.625 | G39: 62141.689 | H39: 62108.752
B40: Check | C40: =IF(C37=G5,"Ok","Check") -> Ok
C41: Equity value per share
C42: ω
C43: =D28 -> 64376.925 | D43: =E43-0.1 -> 0.3 | E43: =F43-0.1 -> 0.4 | F43: 0.5 | G43: =F43+0.1 -> 0.6 | H43: =G43+0.1 -> 0.7
B44: Discount rate | C44: =C45-0.005 -> 0.099998237 | D44: 69852.289 | E44: 68521.195 | F44: 66746.402 | G44: 64261.689 | H44: 60534.614
C45: =C46-0.005 -> 0.10499824 | D45: 68701.048 | E45: 67344.698 | F45: 65539.967 | G45: 63020.488 | H45: 59256.816
C46: 0.10999824 | D46: 67587.466 | E46: 66208.29 | F46: 64376.925 | G46: 61827.374 | H46: 58034.135
C47: =C46+0.005 -> 0.11499824 | D47: 66510.279 | E47: 65110.566 | F47: 63255.66 | G47: 60680.4 | H47: 56864.046
C48: =C47+0.005 -> 0.11999824 | D48: 65468.271 | E48: 64050.174 | F48: 62174.625 | G48: 59577.708 | H48: 55744.16
B49: Check | C49: =IF(C46=G5,"Ok","Check") -> Ok

Sheet MVAM
B2: Market Value Added Valuation
B3: $ and shares in thousands, except per share
B5: Most recent fiscal year end | C5: =FCFM!C4 -> 46053 | E5: WACC | G5: 0.10974247
B6: end of first fiscal year | C6: =FCFM!C5 -> 46053 | E6: Share price | G6: {=_xll.BDP("VEEV US EQUITY", "PX_Last")} -> #NAME?
B7: most recent quarter end date | E7: Share price date | G7: =TODAY() -> 46187
B8: Valuation date | C8: =FCFM!C7 -> 46149
B10: Residual Income
B11: Fiscal year | D11: 2025E | E11: 2026E | F11: 2027E | G11: 2028E | H11: 2029E | I11: 2030E
B12: Fiscal year end date | D12: 46022 | E12: 46387 | F12: 46752 | G12: 47118 | H12: 47483 | I12: 47848
E14: 1 Yr- Target | F14: 1 | G14: 2 | H14: 3 | I14: 4
E15: =EOMONTH(C8,12) -> 46538 | F15: 46752 | G15: 47118 | H15: 47483 | I15: 47848
B16: NOPAT | E16: =FCFM!F23 -> 36380.879 | F16: =FCFM!G23 -> 41052.044 | G16: =FCFM!H23 -> 41129.464 | H16: =FCFM!I23 -> 35326.946 | I16: =FCFM!J23 -> 21522.85 | J16: =I16*(1+D23) -> 22060.922
B17: CAPITAL | E17: =SUM(FSM!F72:F75,FSM!F66,FSM!F68) -> 1.9168978e+10 | F17: =SUM(FSM!G72:G75,FSM!G66,FSM!G68) -> 1.9169368e+10 | G17: =SUM(FSM!H72:H75,FSM!H66,FSM!H68) -> 1.916993e+10 | H17: =SUM(FSM!I72:I75,FSM!I66,FSM!I68) -> 1.9170581e+10 | I17: =SUM(FSM!J72:J75,FSM!J66,FSM!J68) -> 1.9171241e+10
B18: EROIC | F18: =G16/F17 -> 2.1455827e-06 | G18: =H16/G17 -> 1.8428313e-06 | H18: =I16/H17 -> 1.122702e-06 | I18: =J16/I17 -> 1.1507299e-06
B19: Market Value Added | F19: =F17*(F18-$G$5) -> -2.1036527e+09 | G19: =G17*(G18-$G$5) -> -2.1037202e+09 | H19: =H17*(H18-$G$5) -> -2.1038055e+09 | I19: =I17*(I18-$G$5) -> -2.1038774e+09
B20: Present value of Market Value Added | F20: =F19/(1+$G$5)^((F15-E15)/365) -> -1.9790656e+09 | G20: =G19/(1+$G$5)^((G15-F15)/365) -> -1.8951425e+09 | H20: =H19/(1+$G$5)^((H15-G15)/365) -> -1.8957601e+09 | I20: =I19/(1+$G$5)^((I15-H15)/365) -> -1.8958249e+09
B22: Terminal value- growth to perpetuity
B23: Long term growth rate | D23: =FCFM!D42 -> 0.025
B24: 2031 MVA | D24: =I20*(1+D23) -> -1.9432205e+09
B25: Terminal value in 2030 | D25: =D24/(G5-D23) -> -2.2930892e+10
B26: Present value of terminal value | D26: =D25/(1+$G$5)^((I15-E15)/365) -> -1.5780348e+10
B27: Present value of stage 1 cash flows | D27: =SUM(G20:I20) -> -5.6867274e+09
B28: Capital 2026 | D28: =E17 -> 1.9168978e+10
B29: Total enterprise value (TEV) | D29: =SUM(D26:D28) -> -2.2980978e+09
B31: Terminal value as % of TEV | D31: =D26/D29 -> 6.8666999
B32: Stage 1 cash flows as % of TEV | D32: =(D27+D28)/D29 -> -5.8666999
B34: Net debt
B35: Source document | D35: 10-K
B36: Source date | D36: 46066
B37: Gross debt and equivalents
B38: Debt | D38: =FCFM!D57 -> 95859
B39: Minority Interest | D39: =FCFM!D58 -> 0
B40: Preferred stock | D40: =FCFM!D59 -> 0
B41: Nonoperating assets
B42: Cash | D42: =FCFM!D61 -> 6560814
B44: Net debt | D44: =SUM(D38:D40)-D42 -> -6464955
B46: Valuation- growth to perpetuity
B47: Enterprise value | D47: =D29 -> -2.2980978e+09
B48: Net debt | D48: =D44 -> -6464955
B49: Equity value | D49: =D47-D48 -> -2.2916329e+09
B50: Shares outstanding | D50: =FCFM!J46 -> 178465.81
B51: Equity price per share | D51: =D49/D50 -> -12840.739
B53: Sensitivity Analysis
C55: Equity value per share
C56: Long term growth rate (g):
C57: =D51 -> -12840.739 | D57: =E57-0.0025 -> 0.02 | E57: =F57-0.0025 -> 0.0225 | F57: 0.025 | G57: =F57+0.0025 -> 0.0275 | H57: =G57+0.0025 -> 0.03
B58: Discount rate | C58: =C59-0.005 -> 0.099742474 | D58: -10370.513 | E58: -13462.012 | F58: -16760.32 | G58: -20286.908 | H58: -24066.326
C59: =C60-0.005 -> 0.10474247 | D59: -8844.873 | E59: -11667.737 | F59: -14667.599 | G59: -17861.646 | H59: -21269.363
C60: 0.10974247 | D60: -7507.0035 | E60: -10097.45 | F60: -12840.739 | G60: -15750.808 | H60: -18843.345
C61: =C60+0.005 -> 0.11474247 | D61: -6329.9202 | E61: -8717.5534 | F61: -11238.214 | G61: -13903.337 | H61: -16725.708
C62: =C61+0.005 -> 0.11974247 | D62: -5291.9077 | E62: -7501.2126 | F62: -9827.1129 | G62: -12279.088 | H62: -14867.676

Sheet Relative Valuation
B2: Company name | D2: VEEV US EQUITY
B3: last closing price | C3: PX_Last | D3: {=_xll.BDP($D$2,C3,"3/2/26")} -> #NAME?
B4: 52 week high | C4: HIGH_52WEEK | D4: {=_xll.BDP($D$2,C4,$C$9)} -> #NAME?
B5: 52 week low | C5: LOW_52WEEK | D5: {=_xll.BDP($D$2,C5,$C$9)} -> #NAME?
B6: Market cap | C6: CUR_MKT_CAP | D6: {=_xll.BDP($D$2,C6,$C$9)/1000000} -> #NAME?
B7: Shares outstanding | C7: EQY_SH_OUT | D7: {=_xll.BDP($D$2,C7,$C$9)} -> #NAME?
B8: YTD return | C8: CHG_PCT_YTD | D8: {=_xll.BDP($D$2,C8,$C$9)} -> #NAME?
D10: Equity 1 | E10: Equity 2 | F10: Equity 3 | G10: Equity 4 | H10: Equity 5 | I10: Peer group average | J10: My company
D11: IQV US EQUITY | E11: CRM US EQUITY | F11: DOCS US EQUITY | G11: MEDP US EQUITY | J11: =D2 -> VEEV US EQUITY
B13: Multiples | K13: Include?
B14: Price to sales ratio | C14: PX_TO_SALES_RATIO | D14: {=_xll.BDP(D$11,$C14)} -> #NAME? | E14: {=_xll.BDP(E$11,$C14)} -> #NAME? | F14: {=_xll.BDP(F$11,$C14)} -> #NAME? | G14: {=_xll.BDP(G$11,$C14)} -> #NAME? | I14: =AVERAGE(D14:H14) -> #NAME? | J14: {=_xll.BDP(J$11,C14)} -> #NAME? | K14: No
B15: Price to book ratio | C15: PX_TO_BOOK_RATIO | D15: {=_xll.BDP(D$11,$C15)} -> #NAME? | E15: {=_xll.BDP(E$11,$C15)} -> #NAME? | F15: {=_xll.BDP(F$11,$C15)} -> #NAME? | G15: {=_xll.BDP(G$11,$C15)} -> #NAME? | I15: =AVERAGE(D15:H15) -> #NAME? | J15: {=_xll.BDP(J$11,C15)} -> #NAME? | K15: Yes
B16: Price to EBITDA | C16: PX_TO_EBITDA | D16: {=_xll.BDP(D$11,$C16)} -> #NAME? | E16: {=_xll.BDP(E$11,$C16)} -> #NAME? | F16: {=_xll.BDP(F$11,$C16)} -> #NAME? | G16: {=_xll.BDP(G$11,$C16)} -> #NAME? | I16: =AVERAGE(D16:H16) -> #NAME? | J16: {=_xll.BDP(J$11,C16)} -> #NAME? | K16: No
B17: Price to FCF | C17: PX_TO_FREE_CASH_FLOW | D17: {=_xll.BDP(D$11,$C17)} -> #NAME? | E17: {=_xll.BDP(E$11,$C17)} -> #NAME? | F17: {=_xll.BDP(F$11,$C17)} -> #NAME? | G17: {=_xll.BDP(G$11,$C17)} -> #NAME? | I17: =AVERAGE(D17:H17) -> #NAME? | J17: {=_xll.BDP(J$11,C17)} -> #NAME? | K17: No
B18: Price to EPS | C18: PX_TO_EPS_BEFORE_ABNORMAL_ITEMS | D18: {=_xll.BDP(D$11,$C18)} -> #NAME? | E18: {=_xll.BDP(E$11,$C18)} -> #NAME? | F18: {=_xll.BDP(F$11,$C18)} -> #NAME? | G18: {=_xll.BDP(G$11,$C18)} -> #NAME? | I18: =AVERAGE(D18:H18) -> #NAME? | J18: {=_xll.BDP(J$11,C18)} -> #NAME? | K18: Yes
B19: EV to trailing 12M sales | C19: EV_TO_T12M_SALES | D19: {=_xll.BDP(D$11,$C19)} -> #NAME? | E19: {=_xll.BDP(E$11,$C19)} -> #NAME? | F19: {=_xll.BDP(F$11,$C19)} -> #NAME? | G19: {=_xll.BDP(G$11,$C19)} -> #NAME? | I19: =AVERAGE(D19:H19) -> #NAME? | J19: {=_xll.BDP(J$11,C19)} -> #NAME? | K19: Yes
B21: Data pull | D21: 44227 | E21: =D21+365 -> 44592 | F21: =E21+365 -> 44957 | G21: =F21+366 -> 45323 | H21: =G21+365 -> 45688
B22: Trailing 12M sales per share | C22: TRAIL_12M_SALES_PER_SH | D22: {=_xll.BDH($D$2,$C22,D$21)} -> 9.7215 | E22: {=_xll.BDH($D$2,$C22,E$21)} -> 12.0754 | F22: {=_xll.BDH($D$2,$C22,F$21)} -> 13.8708 | G22: {=_xll.BDH($D$2,$C22,G$21)} -> #N/A N/A | H22: {=_xll.BDH($D$2,$C22,H$21)} -> 16.966
B23: Trailing 12M net sales | C23: TRAIL_12M_NET_SALES | D23: {=_xll.BDH($D$2,$C23,D$21)} -> 1465.069 | E23: {=_xll.BDH($D$2,$C23,E$21)} -> 1850.777 | F23: {=_xll.BDH($D$2,$C23,F$21)} -> 2155.06 | G23: {=_xll.BDH($D$2,$C23,G$21)} -> #N/A N/A | H23: {=_xll.BDH($D$2,$C23,H$21)} -> 2746.619
B24: Short and long term debt | C24: SHORT_AND_LONG_TERM_DEBT | D24: {=_xll.BDH($D$2,$C24,D$21)} -> 63.118 | E24: {=_xll.BDH($D$2,$C24,E$21)} -> 54.588 | F24: {=_xll.BDH($D$2,$C24,F$21)} -> 60.976 | G24: {=_xll.BDH($D$2,$C24,G$21)} -> #N/A N/A | H24: {=_xll.BDH($D$2,$C24,H$21)} -> 75.775
B25: Cash and cash equivalents | C25: BS_CASH_NEAR_CASH_ITEM | D25: {=_xll.BDH($D$2,$C25,D$21)} -> 730.504 | E25: {=_xll.BDH($D$2,$C25,E$21)} -> 1138.04 | F25: {=_xll.BDH($D$2,$C25,F$21)} -> 886.465 | G25: {=_xll.BDH($D$2,$C25,G$21)} -> #N/A N/A | H25: {=_xll.BDH($D$2,$C25,H$21)} -> 1118.785
B26: Book value per share | C26: BOOK_VAL_PER_SH | D26: {=_xll.BDH($D$2,$C26,D$21)} -> 14.9044 | E26: {=_xll.BDH($D$2,$C26,E$21)} -> 20.882 | F26: {=_xll.BDH($D$2,$C26,F$21)} -> 23.4842 | G26: {=_xll.BDH($D$2,$C26,G$21)} -> #N/A N/A | H26: {=_xll.BDH($D$2,$C26,H$21)} -> 35.873
B27: EPS from Continuing Operations | C27: T12_EPS_CONT_OPS | D27: {=_xll.BDH($D$2,$C27,D$21)} -> 2.52 | E27: {=_xll.BDH($D$2,$C27,E$21)} -> 2.79 | F27: {=_xll.BDH($D$2,$C27,F$21)} -> 3.13 | G27: {=_xll.BDH($D$2,$C27,G$21)} -> #N/A N/A | H27: {=_xll.BDH($D$2,$C27,H$21)} -> 4.2833
B28: Trailing 12M FCF per share | C28: TRAIL_12M_FREE_CASH_FLOW_PER_SH | D28: {=_xll.BDH($D$2,$C28,D$21)} -> 3.6101 | E28: {=_xll.BDH($D$2,$C28,E$21)} -> 4.9101 | F28: {=_xll.BDH($D$2,$C28,F$21)} -> 4.9514 | G28: {=_xll.BDH($D$2,$C28,G$21)} -> #N/A N/A | H28: {=_xll.BDH($D$2,$C28,H$21)} -> 6.6189
B29: Trailing 12M EBITDA per share | C29: TRAIL_12M_EBITDA_PER_SHARE | D29: {=_xll.BDH($D$2,$C29,D$21)} -> 2.7888 | E29: {=_xll.BDH($D$2,$C29,E$21)} -> 3.5627 | F29: {=_xll.BDH($D$2,$C29,F$21)} -> 3.2462 | G29: {=_xll.BDH($D$2,$C29,G$21)} -> #N/A N/A | H29: {=_xll.BDH($D$2,$C29,H$21)} -> 4.6005
B31: Multiple | D31: Competitors' averages | E31: Price
B32: Price to sales ratio | D32: =I14 -> #NAME? | E32: =IF(K14="Yes",D32*H22,"")
B33: Price to book ratio | D33: =I15 -> #NAME? | E33: =IF(K15="Yes",D33*H26,"") -> #NAME?
B34: Price to EBITDA | D34: =I16 -> #NAME? | E34: =IF(K16="Yes",D34*H29,"")
B35: Price to FCF | D35: =I17 -> #NAME? | E35: =IF(K17="Yes",D35*H28,"")
B36: Price to EPS | D36: =I18 -> #NAME? | E36: =IF(K18="Yes",D36*H27,"") -> #NAME?
B37: EV to trailing 12M sales | D37: =I19 -> #NAME? | E37: =IF(K19="Yes",((D37*H23)-H24+H25)/D7,"") -> #NAME?
B38: Final target price | E38: =AVERAGE(E32:E37) -> #NAME?
B40: Last Price | E40: =D3 -> #NAME?
B41: Potential Upside | E41: =E38/E40-1 -> #NAME?

Sheet Blended Valuation
B2: Models | C2: 12-month Price Target | D2: Weight | E2: Include?
B3: FCFM | C3: =FCFM!D70 -> 4564.7415 | D3: 0.25 | E3: Yes
B4: RIM | C4: =RIM!D28 -> 64376.925 | D4: 0.125 | E4: Yes
B5: MVAM | C5: =MVAM!D51 -> -12840.739 | D5: 0.125 | E5: Yes
B6: COMPS | C6: ='Relative Valuation'!E38 -> #NAME? | D6: 0.5 | E6: Yes
B7: 12 Month Target Price | D7: =SUM(D3:D6) -> 1
B9: Models | C9: Weighted Valuation | F9: Current Price | G9: =FCFM!G5 -> #NAME?
B10: FCFM | C10: =IF(E3="Yes",C3*D3,0) -> 1141.1854 | F10: 12-Month Target | G10: =C14 -> #NAME?
B11: RIM | C11: =IF(E4="Yes",C4*D4,0) -> 8047.1156 | F11: Return | G11: =G10/G9-1 -> #NAME?
B12: MVAM | C12: =IF(E5="Yes",C5*D5,0) -> -1605.0924
B13: COMPS | C13: =IF(E6="Yes",C6*D6,0) -> #NAME?
B14: Blended 12-month price target | C14: =SUM(C10:C13) -> #NAME?
B15: Potential Upside
B17: Football Field
C18: Low | D18: Difference | E18: High
B19: FCFM | C19: =MIN(FCFM!D82:H86) -> 3246.9085 | D19: =E19-C19 -> 1312.4737 | E19: =MAX(FCFM!D82:H86) -> 4559.3823
B20: RIM | C20: =MIN(RIM!D35:H39,RIM!D44:H48) -> 55744.16 | D20: =E20-C20 -> 14108.129 | E20: =MAX(RIM!D35:H39,RIM!D44:H48) -> 69852.289
B21: MVAM | C21: =MIN(MVAM!D58:H62) -> -24066.326 | D21: =E21-C21 -> 18774.419 | E21: =MAX(MVAM!D58:H62) -> -5291.9077
B22: COMPS | C22: =0.95*C6 -> #NAME? | D22: =E22-C22 -> #NAME? | E22: =1.05*C6 -> #NAME?

Sheet WACC
B2: Ticker | C2: Levered Beta | D2: Tax Rate | E2: Debt/Equity | F2: Unlevered Beta | G2: Cash | H2: Firm Value | I2: Cash/ firm value | J2: Cash adj. unl beta
B3: IQV US EQUITY | C3: 1.12 | D3: {=_xll.BDP($B3,$N$9)/100} -> #NAME? | E3: {=_xll.BDP($B3,$N$9)/100} -> #NAME? | F3: =C3/(1+(1-D3)*E3) -> #NAME? | G3: {=_xll.BDP($B3,$N$11)} -> #NAME? | H3: {=_xll.BDP($B3,$N$12)} -> #NAME? | I3: =G3/H3 -> #NAME? | J3: =F3/(1-I3) -> #NAME?
B4: CRM US EQUITY | C4: 1.094 | D4: {=_xll.BDP($B4,$N$9)/100} -> #NAME? | E4: {=_xll.BDP($B4,$N$9)/100} -> #NAME? | F4: =C4/(1+(1-D4)*E4) -> #NAME? | G4: {=_xll.BDP($B4,$N$11)} -> #NAME? | H4: {=_xll.BDP($B4,$N$12)} -> #NAME? | I4: =G4/H4 -> #NAME? | J4: =F4/(1-I4) -> #NAME? | N4: {=_xll.BDP(N13,N11)} -> #NAME?
B5: DOCS US EQUITY | C5: 1.235 | D5: {=_xll.BDP($B5,$N$9)/100} -> #NAME? | E5: {=_xll.BDP($B5,$N$9)/100} -> #NAME? | F5: =C5/(1+(1-D5)*E5) -> #NAME? | G5: {=_xll.BDP($B5,$N$11)} -> #NAME? | H5: {=_xll.BDP($B5,$N$12)} -> #NAME? | I5: =G5/H5 -> #NAME? | J5: =F5/(1-I5) -> #NAME? | N5: {=_xll.BDP(N13,N12)} -> #NAME?
B6: MEDP US EQUITY | C6: 1.311 | D6: {=_xll.BDP($B6,$N$9)/100} -> #NAME? | E6: {=_xll.BDP($B6,$N$9)/100} -> #NAME? | F6: =C6/(1+(1-D6)*E6) -> #NAME? | G6: {=_xll.BDP($B6,$N$11)} -> #NAME? | H6: {=_xll.BDP($B6,$N$12)} -> #NAME? | I6: =G6/H6 -> #NAME? | J6: =F6/(1-I6) -> #NAME? | N6: =N4/N5 -> #NAME?
B7: ORCL US EQUITY | C7: 1.363 | D7: {=_xll.BDP($B7,$N$9)/100} -> #NAME? | E7: {=_xll.BDP($B7,$N$9)/100} -> #NAME? | F7: =C7/(1+(1-D7)*E7) -> #NAME? | G7: {=_xll.BDP($B7,$N$11)} -> #NAME? | H7: {=_xll.BDP($B7,$N$12)} -> #NAME? | I7: =G7/H7 -> #NAME? | J7: =F7/(1-I7) -> #NAME?
I8: Average | J8: =AVERAGE(J3:J7) -> #NAME?
B9: Cost of Equity | I9: VEEV cash/firm value | J9: =N6 -> #NAME? | N9: EFF_TAX_RATE
B10: Rrf | C10: {=_xll.BDP(N14,"PX_LAST")/100} -> #NAME? | I10: VEEV unlevered beta | J10: =J8*(1-J9) -> #NAME? | N10: TOT_DEBT_TO_TOT_EQY
B11: B | C11: =J13 -> #NAME? | I11: VEEV tax rate | J11: {=_xll.BDP(N13,N9)/100} -> #NAME? | N11: CASH_AND_MARKETABLE_SECURITIES
B12: ERP | C12: 0.0808 | I12: D/E Ratio | J12: {=_xll.BDP(N13,N10)/100} -> #NAME? | N12: CURR_ENTP_VAL
B13: Cost of E | C13: =C10+C11*C12 -> #NAME? | I13: VEEV levered beta | J13: =J10*(1+(1-J11)*J12) -> #NAME? | N13: VEEV US EQUITY
N14: USGG10YR Index
B15: Cost of Debt
B16: pre-tax cost | C16: 0.048 | N16: CUR_MKT_CAP
B17: tax rate | C17: =J11 -> #NAME?
B18: post-tax cost | C18: =C16*(1-C17) -> #NAME? | N18: {=_xll.BDP(N13,N16)} -> #NAME?
N19: =N18/1000 -> #NAME?
B20: Debt | C20: =FSM!E66+FSM!E68 -> 95859
B21: Equity | C21: =N19 -> #NAME?
B23: Wd | C23: =C20/SUM(C20:C21) -> #NAME? | E23: 0.2
B24: We | C24: =C21/SUM(C20:C21) -> #NAME? | E24: 0.8
B26: WACC | C26: =C23*C18+C24*C13 -> #NAME?
B28: Rs | C28: 0.10999824
B29: WACC | C29: 0.10974247 | E29: =E23*C18+E24*C13 -> #NAME?
